[
  {
    "id": 659170,
    "username": "Banned Porridge",
    "winsRanked": 3,
    "lossesRanked": 0,
    "division": "DIAMOND_IV",
    "level": 114,
    "eloRanked": 1920,
    "eloChange": -331,
    "rankChange": 3,
    "wins": -139,
    "losses": -62,
    "rank": 1
  },
  {
    "id": 361226,
    "username": "Punai",
    "winsRanked": 2,
    "lossesRanked": 0,
    "division": "RUBY_II",
    "level": 1278,
    "eloRanked": 1868,
    "eloChange": -307,
    "rankChange": 10,
    "wins": -67,
    "losses": -15,
    "rank": 2
  },
  {
    "id": 413682,
    "username": "notBihapove",
    "winsRanked": 4,
    "lossesRanked": 0,
    "division": "RUBY_II",
    "level": 245,
    "eloRanked": 1850,
    "eloChange": -264,
    "rankChange": 17,
    "wins": -43,
    "losses": -3,
    "rank": 3
  },
  {
    "id": 342410,
    "username": "finpom",
    "winsRanked": 4,
    "lossesRanked": 2,
    "division": "RUBY_III",
    "level": 500,
    "eloRanked": 1825,
    "eloChange": -279,
    "rankChange": 19,
    "wins": -91,
    "losses": -52,
    "rank": 4
  },
  {
    "id": 366840,
    "username": "MatthewTDAM",
    "winsRanked": 2,
    "lossesRanked": 2,
    "division": "AMETHYST_I",
    "level": 598,
    "eloRanked": 1784,
    "eloChange": -287,
    "rankChange": 23,
    "wins": -287,
    "losses": -203,
    "rank": 5
  },
  {
    "id": 455724,
    "username": ".(^-^) .",
    "winsRanked": 1,
    "lossesRanked": 0,
    "division": "AMETHYST_I",
    "level": 726,
    "eloRanked": 1780,
    "eloChange": -264,
    "rankChange": 46,
    "wins": -62,
    "losses": -42,
    "rank": 6
  },
  {
    "id": 515615,
    "username": "Daddy",
    "winsRanked": 1,
    "lossesRanked": 0,
    "division": "AMETHYST_II",
    "level": 522,
    "eloRanked": 1765,
    "eloChange": -268,
    "rankChange": 56,
    "wins": -77,
    "losses": -52,
    "rank": 7
  },
  {
    "id": 650820,
    "username": "YOFCA",
    "winsRanked": 2,
    "lossesRanked": 3,
    "division": "AMETHYST_II",
    "level": 456,
    "eloRanked": 1762,
    "eloChange": -279,
    "rankChange": 46,
    "wins": -518,
    "losses": -300,
    "rank": 8
  },
  {
    "id": 326285,
    "username": "Seto",
    "winsRanked": 1,
    "lossesRanked": 1,
    "division": "AMETHYST_II",
    "level": 2004,
    "eloRanked": 1759,
    "eloChange": -284,
    "rankChange": 44,
    "wins": -470,
    "losses": -422,
    "rank": 9
  },
  {
    "id": 370081,
    "username": "Demon Divergent",
    "winsRanked": 2,
    "lossesRanked": 0,
    "division": "AMETHYST_II",
    "level": 2435,
    "eloRanked": 1753,
    "eloChange": -248,
    "rankChange": 136,
    "wins": -29,
    "losses": -7,
    "rank": 10
  },
  {
    "id": 37987,
    "username": "Ethy",
    "winsRanked": 1,
    "lossesRanked": 0,
    "division": "AMETHYST_II",
    "level": 406,
    "eloRanked": 1753,
    "eloChange": -258,
    "rankChange": 83,
    "wins": -27,
    "losses": -8,
    "rank": 11
  },
  {
    "id": 433216,
    "username": "AG",
    "winsRanked": 0,
    "lossesRanked": 1,
    "division": "AMETHYST_II",
    "level": 1146,
    "eloRanked": 1752,
    "eloChange": -294,
    "rankChange": 38,
    "wins": -132,
    "losses": -99,
    "rank": 12
  },
  {
    "id": 653864,
    "username": "Annoying Dummy",
    "winsRanked": 1,
    "lossesRanked": 0,
    "division": "AMETHYST_II",
    "level": 195,
    "eloRanked": 1751,
    "eloChange": -254,
    "rankChange": 106,
    "wins": -50,
    "losses": -29,
    "rank": 13
  },
  {
    "id": 427478,
    "username": "PK Moritz",
    "winsRanked": 2,
    "lossesRanked": 1,
    "division": "AMETHYST_II",
    "level": 430,
    "eloRanked": 1750,
    "eloChange": -253,
    "rankChange": 124,
    "wins": -85,
    "losses": -85,
    "rank": 14
  },
  {
    "id": 479670,
    "username": "ItsAlex",
    "winsRanked": 1,
    "lossesRanked": 3,
    "division": "AMETHYST_II",
    "level": 610,
    "eloRanked": 1750,
    "eloChange": -279,
    "rankChange": 51,
    "wins": -61,
    "losses": -47,
    "rank": 15
  },
  {
    "id": 636302,
    "username": "The_D6(!)",
    "winsRanked": 1,
    "lossesRanked": 0,
    "division": "AMETHYST_III",
    "level": 159,
    "eloRanked": 1743,
    "eloChange": -259,
    "rankChange": 127,
    "wins": -84,
    "losses": -62,
    "rank": 16
  },
  {
    "id": 617462,
    "username": "FindingDeath",
    "winsRanked": 1,
    "lossesRanked": 1,
    "division": "AMETHYST_III",
    "level": 75,
    "eloRanked": 1738,
    "eloChange": -263,
    "rankChange": 133,
    "wins": -50,
    "losses": -25,
    "rank": 17
  },
  {
    "id": 657151,
    "username": "belonata",
    "winsRanked": 1,
    "lossesRanked": 1,
    "division": "AMETHYST_III",
    "level": 126,
    "eloRanked": 1732,
    "eloChange": -275,
    "rankChange": 90,
    "wins": -134,
    "losses": -120,
    "rank": 18
  },
  {
    "id": 615842,
    "username": "QPX",
    "winsRanked": 1,
    "lossesRanked": 3,
    "division": "AMETHYST_III",
    "level": 187,
    "eloRanked": 1725,
    "eloChange": -280,
    "rankChange": 103,
    "wins": -74,
    "losses": -62,
    "rank": 19
  },
  {
    "id": 477652,
    "username": "Mr.Mime",
    "winsRanked": 1,
    "lossesRanked": 4,
    "division": "AMETHYST_III",
    "level": 747,
    "eloRanked": 1725,
    "eloChange": -281,
    "rankChange": 97,
    "wins": -188,
    "losses": -170,
    "rank": 20
  },
  {
    "id": 665674,
    "username": "Crisptian",
    "winsRanked": 0,
    "lossesRanked": 2,
    "division": "AMETHYST_III",
    "level": 243,
    "eloRanked": 1725,
    "eloChange": -275,
    "rankChange": 149,
    "wins": -281,
    "losses": -233,
    "rank": 21
  },
  {
    "id": 642923,
    "username": "Sparing962",
    "winsRanked": 0,
    "lossesRanked": 2,
    "division": "AMETHYST_III",
    "level": 52,
    "eloRanked": 1725,
    "eloChange": -275,
    "rankChange": 144,
    "wins": -42,
    "losses": -26,
    "rank": 22
  },
  {
    "id": 314156,
    "username": "ChaosHJohnson",
    "winsRanked": 0,
    "lossesRanked": 1,
    "division": "SAPPHIRE_I",
    "level": 86,
    "eloRanked": 1681,
    "eloChange": -256,
    "rankChange": 179,
    "wins": -144,
    "losses": -175,
    "rank": 23
  },
  {
    "id": 658680,
    "username": "magedeskiwis",
    "winsRanked": 1,
    "lossesRanked": 1,
    "division": "SAPPHIRE_I",
    "level": 151,
    "eloRanked": 1675,
    "eloChange": -225,
    "rankChange": 218,
    "wins": -65,
    "losses": -77,
    "rank": 24
  },
  {
    "id": 209152,
    "username": "Lurker",
    "winsRanked": 2,
    "lossesRanked": 0,
    "division": "SAPPHIRE_II",
    "level": 761,
    "eloRanked": 1673,
    "eloChange": -193,
    "rankChange": 258,
    "wins": -19,
    "losses": -14,
    "rank": 25
  },
  {
    "id": 556074,
    "username": "Sernon158",
    "winsRanked": 1,
    "lossesRanked": 1,
    "division": "SAPPHIRE_II",
    "level": 415,
    "eloRanked": 1668,
    "eloChange": -232,
    "rankChange": 215,
    "wins": -46,
    "losses": -47,
    "rank": 26
  },
  {
    "id": 337474,
    "username": "Nissan101",
    "winsRanked": 1,
    "lossesRanked": 2,
    "division": "SAPPHIRE_II",
    "level": 570,
    "eloRanked": 1665,
    "eloChange": -235,
    "rankChange": 209,
    "wins": -40,
    "losses": -23,
    "rank": 27
  },
  {
    "id": 650580,
    "username": "Nonnono",
    "winsRanked": 2,
    "lossesRanked": 0,
    "division": "SAPPHIRE_II",
    "level": 47,
    "eloRanked": 1659,
    "eloChange": -188,
    "rankChange": 282,
    "wins": -49,
    "losses": -49,
    "rank": 28
  },
  {
    "id": 452931,
    "username": "Nagasriel",
    "winsRanked": 1,
    "lossesRanked": 0,
    "division": "SAPPHIRE_III",
    "level": 518,
    "eloRanked": 1641,
    "eloChange": -209,
    "rankChange": 279,
    "wins": -38,
    "losses": -54,
    "rank": 29
  },
  {
    "id": 73763,
    "username": "worlit",
    "winsRanked": 2,
    "lossesRanked": 1,
    "division": "SAPPHIRE_III",
    "level": 80,
    "eloRanked": 1638,
    "eloChange": -198,
    "rankChange": 307,
    "wins": -56,
    "losses": -78,
    "rank": 30
  },
  {
    "id": 399538,
    "username": "Azamat111",
    "winsRanked": 1,
    "lossesRanked": 0,
    "division": "SAPPHIRE_III",
    "level": 236,
    "eloRanked": 1637,
    "eloChange": -198,
    "rankChange": 307,
    "wins": -25,
    "losses": -7,
    "rank": 31
  },
  {
    "id": 489217,
    "username": "Avatarshow",
    "winsRanked": 1,
    "lossesRanked": 2,
    "division": "SAPPHIRE_III",
    "level": 566,
    "eloRanked": 1637,
    "eloChange": -231,
    "rankChange": 250,
    "wins": -61,
    "losses": -81,
    "rank": 32
  },
  {
    "id": 660916,
    "username": "giasfelfebreher",
    "winsRanked": 1,
    "lossesRanked": 0,
    "division": "SAPPHIRE_III",
    "level": 125,
    "eloRanked": 1636,
    "eloChange": -201,
    "rankChange": 302,
    "wins": -67,
    "losses": -117,
    "rank": 33
  },
  {
    "id": 672115,
    "username": "Luna van Yeet",
    "winsRanked": 1,
    "lossesRanked": 0,
    "division": "SAPPHIRE_III",
    "level": 33,
    "eloRanked": 1628,
    "eloChange": -210,
    "rankChange": 296,
    "wins": -49,
    "losses": -34,
    "rank": 34
  },
  {
    "id": 510537,
    "username": "luario_fanboy2",
    "winsRanked": 0,
    "lossesRanked": 1,
    "division": "SAPPHIRE_III",
    "level": 192,
    "eloRanked": 1628,
    "eloChange": -234,
    "rankChange": 256,
    "wins": -36,
    "losses": -49,
    "rank": 35
  },
  {
    "id": 617391,
    "username": "Foner007674",
    "winsRanked": 2,
    "lossesRanked": 0,
    "division": "SAPPHIRE_III",
    "level": 84,
    "eloRanked": 1627,
    "eloChange": -173,
    "rankChange": 507,
    "wins": -69,
    "losses": -117,
    "rank": 36
  },
  {
    "id": 497375,
    "username": "Pw32",
    "winsRanked": 0,
    "lossesRanked": 2,
    "division": "SAPPHIRE_III",
    "level": 403,
    "eloRanked": 1625,
    "eloChange": -215,
    "rankChange": 288,
    "wins": -40,
    "losses": -35,
    "rank": 37
  },
  {
    "id": 42889,
    "username": "NeoSaysMeow",
    "winsRanked": 0,
    "lossesRanked": 2,
    "division": "SAPPHIRE_III",
    "level": 276,
    "eloRanked": 1625,
    "eloChange": -234,
    "rankChange": 256,
    "wins": -80,
    "losses": -147,
    "rank": 38
  },
  {
    "id": 673244,
    "username": "HelloILikePuns",
    "winsRanked": 2,
    "lossesRanked": 1,
    "division": "SAPPHIRE_IV",
    "level": 27,
    "eloRanked": 1614,
    "eloChange": -189,
    "rankChange": 418,
    "wins": -47,
    "losses": -35,
    "rank": 39
  },
  {
    "id": 135722,
    "username": "undauntedgunner",
    "winsRanked": 1,
    "lossesRanked": 0,
    "division": "SAPPHIRE_IV",
    "level": 572,
    "eloRanked": 1613,
    "eloChange": -188,
    "rankChange": 442,
    "wins": -20,
    "losses": -18,
    "rank": 40
  },
  {
    "id": 560577,
    "username": "revanswrath2003",
    "winsRanked": 0,
    "lossesRanked": 1,
    "division": "SAPPHIRE_IV",
    "level": 326,
    "eloRanked": 1607,
    "eloChange": -224,
    "rankChange": 302,
    "wins": -30,
    "losses": -43,
    "rank": 41
  },
  {
    "id": 457899,
    "username": "GlassLeaf",
    "winsRanked": 1,
    "lossesRanked": 1,
    "division": "SAPPHIRE_IV",
    "level": 126,
    "eloRanked": 1602,
    "eloChange": -198,
    "rankChange": 479,
    "wins": -46,
    "losses": -54,
    "rank": 42
  },
  {
    "id": 653949,
    "username": "Levich2007",
    "winsRanked": 1,
    "lossesRanked": 2,
    "division": "SAPPHIRE_IV",
    "level": 61,
    "eloRanked": 1600,
    "eloChange": -204,
    "rankChange": 410,
    "wins": -33,
    "losses": -32,
    "rank": 43
  },
  {
    "id": 55540,
    "username": "coreyarmy",
    "winsRanked": 0,
    "lossesRanked": 1,
    "division": "SAPPHIRE_IV",
    "level": 1437,
    "eloRanked": 1600,
    "eloChange": -200,
    "rankChange": 495,
    "wins": -93,
    "losses": -139,
    "rank": 44
  },
  {
    "id": 610182,
    "username": "Kirby05",
    "winsRanked": 0,
    "lossesRanked": 1,
    "division": "SAPPHIRE_IV",
    "level": 470,
    "eloRanked": 1600,
    "eloChange": -208,
    "rankChange": 388,
    "wins": -33,
    "losses": -66,
    "rank": 45
  },
  {
    "id": 593503,
    "username": "Stryker_",
    "winsRanked": 0,
    "lossesRanked": 1,
    "division": "SAPPHIRE_IV",
    "level": 40,
    "eloRanked": 1600,
    "eloChange": -209,
    "rankChange": 380,
    "wins": -46,
    "losses": -29,
    "rank": 46
  },
  {
    "id": 631879,
    "username": "Hyper!Dust!Elmo",
    "winsRanked": 0,
    "lossesRanked": 1,
    "division": "EMERALD_I",
    "level": 37,
    "eloRanked": 1575,
    "eloChange": -189,
    "rankChange": 545,
    "wins": -38,
    "losses": -26,
    "rank": 47
  },
  {
    "id": 661931,
    "username": "Cyb3rD1va",
    "winsRanked": 1,
    "lossesRanked": 0,
    "division": "EMERALD_II",
    "level": 38,
    "eloRanked": 1563,
    "eloChange": -162,
    "rankChange": 629,
    "wins": -56,
    "losses": -73,
    "rank": 48
  },
  {
    "id": 533368,
    "username": "Warrior1234",
    "winsRanked": 1,
    "lossesRanked": 0,
    "division": "EMERALD_II",
    "level": 147,
    "eloRanked": 1555,
    "eloChange": -144,
    "rankChange": 696,
    "wins": -46,
    "losses": -47,
    "rank": 49
  },
  {
    "id": 597334,
    "username": "issac go brr",
    "winsRanked": 0,
    "lossesRanked": 1,
    "division": "EMERALD_II",
    "level": 89,
    "eloRanked": 1550,
    "eloChange": -187,
    "rankChange": 596,
    "wins": -52,
    "losses": -71,
    "rank": 50
  },
  {
    "id": 602537,
    "username": "Chara The First",
    "winsRanked": 1,
    "lossesRanked": 3,
    "division": "EMERALD_III",
    "level": 39,
    "eloRanked": 1525,
    "eloChange": -150,
    "rankChange": 748,
    "wins": -49,
    "losses": -80,
    "rank": 51
  },
  {
    "id": 376134,
    "username": "Negie",
    "winsRanked": 0,
    "lossesRanked": 2,
    "division": "GOLD_I",
    "level": 151,
    "eloRanked": 1483,
    "eloChange": -142,
    "rankChange": 859,
    "wins": -26,
    "losses": -14,
    "rank": 52
  },
  {
    "id": 671848,
    "username": "Franimer",
    "winsRanked": 0,
    "lossesRanked": 1,
    "division": "GOLD_II",
    "level": 28,
    "eloRanked": 1469,
    "eloChange": -135,
    "rankChange": 916,
    "wins": -30,
    "losses": -26,
    "rank": 53
  },
  {
    "id": 643848,
    "username": "heavy_alter",
    "winsRanked": 0,
    "lossesRanked": 1,
    "division": "GOLD_II",
    "level": 36,
    "eloRanked": 1454,
    "eloChange": -124,
    "rankChange": 991,
    "wins": -29,
    "losses": -29,
    "rank": 54
  },
  {
    "id": 488833,
    "username": "Eeveefire",
    "winsRanked": 1,
    "lossesRanked": 1,
    "division": "GOLD_IV",
    "level": 92,
    "eloRanked": 1419,
    "eloChange": -81,
    "rankChange": 1356,
    "wins": -7,
    "losses": -33,
    "rank": 55
  },
  {
    "id": 672218,
    "username": "Akeduardo 22",
    "winsRanked": 0,
    "lossesRanked": 1,
    "division": "GOLD_IV",
    "level": 26,
    "eloRanked": 1416,
    "eloChange": -109,
    "rankChange": 1198,
    "wins": -22,
    "losses": -27,
    "rank": 56
  },
  {
    "id": 562791,
    "username": "P7778",
    "winsRanked": 1,
    "lossesRanked": 0,
    "division": "GOLD_IV",
    "level": 56,
    "eloRanked": 1407,
    "eloChange": -93,
    "rankChange": 1312,
    "wins": -13,
    "losses": -10,
    "rank": 57
  },
  {
    "id": 674546,
    "username": "Cody2522",
    "winsRanked": 0,
    "lossesRanked": 1,
    "division": "IRON_I",
    "level": 21,
    "eloRanked": 1381,
    "eloChange": -91,
    "rankChange": 1456,
    "wins": -14,
    "losses": -20,
    "rank": 58
  },
  {
    "id": 602612,
    "username": "Xuxu",
    "winsRanked": 1,
    "lossesRanked": 2,
    "division": "IRON_III",
    "level": 217,
    "eloRanked": 1326,
    "rank": 59
  },
  {
    "id": 481723,
    "username": "KawczoX",
    "winsRanked": 1,
    "lossesRanked": 0,
    "division": "COPPER_I",
    "level": 103,
    "eloRanked": 1283,
    "eloChange": -13,
    "rankChange": 2155,
    "wins": 0,
    "losses": -2,
    "rank": 60
  },
  {
    "id": 516362,
    "username": "MrIncognito",
    "winsRanked": 3,
    "lossesRanked": 0,
    "division": "COPPER_II",
    "level": 66,
    "eloRanked": 1266,
    "rank": 61
  },
  {
    "id": 369196,
    "username": "Sansyboy1893621",
    "winsRanked": 2,
    "lossesRanked": 0,
    "division": "COPPER_II",
    "level": 33,
    "eloRanked": 1262,
    "eloChange": 11,
    "rankChange": 2403,
    "wins": 1,
    "losses": -4,
    "rank": 62
  },
  {
    "id": 672034,
    "username": "Crimsonnidk",
    "winsRanked": 0,
    "lossesRanked": 1,
    "division": "COPPER_III",
    "level": 21,
    "eloRanked": 1241,
    "eloChange": -21,
    "rankChange": 2326,
    "wins": -3,
    "losses": 0,
    "rank": 63
  },
  {
    "id": 619108,
    "username": "Dedf1sh",
    "winsRanked": 1,
    "lossesRanked": 3,
    "division": "COPPER_IV",
    "level": 18,
    "eloRanked": 1222,
    "rank": 64
  },
  {
    "id": 673208,
    "username": "TimeParadox",
    "winsRanked": 0,
    "lossesRanked": 1,
    "division": "COPPER_IV",
    "level": 10,
    "eloRanked": 1200,
    "eloChange": 0,
    "rankChange": 2993,
    "wins": 0,
    "losses": 0,
    "rank": 65
  }
]