[
  {
    "id": 512212,
    "username": "Catgirl Copycat",
    "winsRanked": 3,
    "lossesRanked": 0,
    "division": "AA",
    "level": 1392,
    "eloRanked": 1864,
    "rank": 1
  },
  {
    "id": 611082,
    "username": "Mustard",
    "winsRanked": 1,
    "lossesRanked": 2,
    "division": "BBB",
    "level": 1200,
    "eloRanked": 1804,
    "rank": 2
  },
  {
    "id": 512395,
    "username": "merun fein",
    "winsRanked": 8,
    "lossesRanked": 1,
    "division": "B",
    "level": 767,
    "eloRanked": 1757,
    "eloChange": 115,
    "rankChange": 0,
    "wins": 7,
    "losses": 1,
    "rank": 3
  },
  {
    "id": 708919,
    "username": "hey",
    "winsRanked": 1,
    "lossesRanked": 1,
    "division": "B",
    "level": 599,
    "eloRanked": 1753,
    "rank": 4
  },
  {
    "id": 628282,
    "username": "lagzendery",
    "winsRanked": 1,
    "lossesRanked": 0,
    "division": "CCC",
    "level": 1004,
    "eloRanked": 1706,
    "rank": 5
  },
  {
    "id": 693352,
    "username": "Gerg747",
    "winsRanked": 1,
    "lossesRanked": 2,
    "division": "CCC",
    "level": 561,
    "eloRanked": 1702,
    "rank": 6
  },
  {
    "id": 741766,
    "username": "Clown in a Cage",
    "winsRanked": 1,
    "lossesRanked": 0,
    "division": "CCC",
    "level": 489,
    "eloRanked": 1701,
    "rank": 7
  },
  {
    "id": 262033,
    "username": "ethannoodle",
    "winsRanked": 2,
    "lossesRanked": 0,
    "division": "CC",
    "level": 668,
    "eloRanked": 1685,
    "eloChange": 0,
    "rankChange": -7,
    "wins": 0,
    "losses": 0,
    "rank": 8
  },
  {
    "id": 247135,
    "username": "Goldbuster",
    "winsRanked": 0,
    "lossesRanked": 3,
    "division": "CC",
    "level": 330,
    "eloRanked": 1670,
    "rank": 9
  },
  {
    "id": 116818,
    "username": "KJSpent200UCP",
    "winsRanked": 3,
    "lossesRanked": 2,
    "division": "C",
    "level": 1050,
    "eloRanked": 1658,
    "eloChange": 18,
    "rankChange": -6,
    "wins": 2,
    "losses": 1,
    "rank": 10
  },
  {
    "id": 431504,
    "username": "Dojo Master",
    "winsRanked": 0,
    "lossesRanked": 2,
    "division": "C",
    "level": 1345,
    "eloRanked": 1643,
    "rank": 11
  },
  {
    "id": 390615,
    "username": "TheLudicrousLuv",
    "winsRanked": 4,
    "lossesRanked": 1,
    "division": "C",
    "level": 1285,
    "eloRanked": 1640,
    "rank": 12
  },
  {
    "id": 515388,
    "username": "66fabian66",
    "winsRanked": 4,
    "lossesRanked": 3,
    "division": "C",
    "level": 224,
    "eloRanked": 1640,
    "rank": 13
  },
  {
    "id": 720046,
    "username": "a_random_person",
    "winsRanked": 1,
    "lossesRanked": 1,
    "division": "C",
    "level": 428,
    "eloRanked": 1640,
    "eloChange": -5,
    "rankChange": -12,
    "wins": 0,
    "losses": 1,
    "rank": 14
  },
  {
    "id": 777443,
    "username": "Common_Sense",
    "winsRanked": 1,
    "lossesRanked": 2,
    "division": "C",
    "level": 97,
    "eloRanked": 1640,
    "rank": 15
  },
  {
    "id": 29091,
    "username": "DerpDerpson",
    "winsRanked": 0,
    "lossesRanked": 1,
    "division": "C",
    "level": 1572,
    "eloRanked": 1640,
    "eloChange": 0,
    "rankChange": -11,
    "wins": 0,
    "losses": 0,
    "rank": 16
  },
  {
    "id": 108160,
    "username": "Domi812",
    "winsRanked": 3,
    "lossesRanked": 3,
    "division": "DDD",
    "level": 1150,
    "eloRanked": 1612,
    "eloChange": 27,
    "rankChange": -11,
    "wins": 3,
    "losses": 2,
    "rank": 17
  },
  {
    "id": 777007,
    "username": "DeltaDr33murr",
    "winsRanked": 4,
    "lossesRanked": 1,
    "division": "DDD",
    "level": 171,
    "eloRanked": 1610,
    "rank": 18
  },
  {
    "id": 568277,
    "username": "apple6392",
    "winsRanked": 3,
    "lossesRanked": 3,
    "division": "DDD",
    "level": 558,
    "eloRanked": 1610,
    "eloChange": 60,
    "rankChange": -11,
    "wins": 3,
    "losses": 1,
    "rank": 19
  },
  {
    "id": 760760,
    "username": "Hanandro",
    "winsRanked": 1,
    "lossesRanked": 2,
    "division": "DDD",
    "level": 325,
    "eloRanked": 1610,
    "rank": 20
  },
  {
    "id": 760173,
    "username": "leuk",
    "winsRanked": 3,
    "lossesRanked": 2,
    "division": "DD",
    "level": 349,
    "eloRanked": 1606,
    "rank": 21
  },
  {
    "id": 514840,
    "username": "Ultrag645",
    "winsRanked": 2,
    "lossesRanked": 1,
    "division": "DD",
    "level": 497,
    "eloRanked": 1581,
    "rank": 22
  },
  {
    "id": 650763,
    "username": "StarFellow23",
    "winsRanked": 1,
    "lossesRanked": 1,
    "division": "D",
    "level": 805,
    "eloRanked": 1573,
    "rank": 23
  },
  {
    "id": 247014,
    "username": "Quent1107",
    "winsRanked": 1,
    "lossesRanked": 0,
    "division": "D",
    "level": 645,
    "eloRanked": 1567,
    "rank": 24
  },
  {
    "id": 747471,
    "username": "UltraCard",
    "winsRanked": 2,
    "lossesRanked": 1,
    "division": "D",
    "level": 761,
    "eloRanked": 1567,
    "rank": 25
  },
  {
    "id": 774138,
    "username": "waycalm",
    "winsRanked": 4,
    "lossesRanked": 0,
    "division": "D",
    "level": 119,
    "eloRanked": 1559,
    "eloChange": 48,
    "rankChange": -15,
    "wins": 2,
    "losses": 0,
    "rank": 26
  },
  {
    "id": 641206,
    "username": "Blaze Dragothan",
    "winsRanked": 3,
    "lossesRanked": 4,
    "division": "D",
    "level": 872,
    "eloRanked": 1554,
    "eloChange": -24,
    "rankChange": -20,
    "wins": 2,
    "losses": 4,
    "rank": 27
  },
  {
    "id": 66304,
    "username": "GabrilmanX",
    "winsRanked": 1,
    "lossesRanked": 1,
    "division": "EEE",
    "level": 2414,
    "eloRanked": 1549,
    "eloChange": 18,
    "rankChange": -18,
    "wins": 1,
    "losses": 0,
    "rank": 28
  },
  {
    "id": 418084,
    "username": "MatheusVH",
    "winsRanked": 1,
    "lossesRanked": 0,
    "division": "EEE",
    "level": 366,
    "eloRanked": 1547,
    "rank": 29
  },
  {
    "id": 671537,
    "username": "BlackBlast20",
    "winsRanked": 1,
    "lossesRanked": 1,
    "division": "EEE",
    "level": 371,
    "eloRanked": 1547,
    "rank": 30
  },
  {
    "id": 763062,
    "username": "Michi2048",
    "winsRanked": 1,
    "lossesRanked": 0,
    "division": "EEE",
    "level": 244,
    "eloRanked": 1540,
    "rank": 31
  },
  {
    "id": 489727,
    "username": "Asra",
    "winsRanked": 4,
    "lossesRanked": 2,
    "division": "EEE",
    "level": 885,
    "eloRanked": 1538,
    "rank": 32
  },
  {
    "id": 767180,
    "username": "katos",
    "winsRanked": 1,
    "lossesRanked": 0,
    "division": "EEE",
    "level": 154,
    "eloRanked": 1535,
    "rank": 33
  },
  {
    "id": 610710,
    "username": "Doctor Worm",
    "winsRanked": 3,
    "lossesRanked": 1,
    "division": "EEE",
    "level": 512,
    "eloRanked": 1531,
    "rank": 34
  },
  {
    "id": 720659,
    "username": "Void866",
    "winsRanked": 4,
    "lossesRanked": 4,
    "division": "EEE",
    "level": 148,
    "eloRanked": 1531,
    "eloChange": -2,
    "rankChange": -26,
    "wins": 3,
    "losses": 4,
    "rank": 35
  },
  {
    "id": 376603,
    "username": "spiritomb8",
    "winsRanked": 0,
    "lossesRanked": 2,
    "division": "EEE",
    "level": 329,
    "eloRanked": 1525,
    "rank": 36
  },
  {
    "id": 164870,
    "username": "Jalapenos78",
    "winsRanked": 2,
    "lossesRanked": 6,
    "division": "EEE",
    "level": 1034,
    "eloRanked": 1522,
    "rank": 37
  },
  {
    "id": 378448,
    "username": "CaramelFrisk",
    "winsRanked": 0,
    "lossesRanked": 1,
    "division": "EEE",
    "level": 378,
    "eloRanked": 1520,
    "rank": 38
  },
  {
    "id": 138171,
    "username": "alsparkb12",
    "winsRanked": 0,
    "lossesRanked": 2,
    "division": "EEE",
    "level": 405,
    "eloRanked": 1520,
    "rank": 39
  },
  {
    "id": 381395,
    "username": "aasadasadas",
    "winsRanked": 1,
    "lossesRanked": 0,
    "division": "EE",
    "level": 281,
    "eloRanked": 1506,
    "rank": 40
  },
  {
    "id": 662773,
    "username": "Dnom",
    "winsRanked": 1,
    "lossesRanked": 0,
    "division": "EE",
    "level": 779,
    "eloRanked": 1498,
    "rank": 41
  },
  {
    "id": 776365,
    "username": "image_freaky",
    "winsRanked": 1,
    "lossesRanked": 0,
    "division": "EE",
    "level": 168,
    "eloRanked": 1493,
    "eloChange": 0,
    "rankChange": -29,
    "wins": 0,
    "losses": 0,
    "rank": 42
  },
  {
    "id": 361868,
    "username": "The senpai",
    "winsRanked": 1,
    "lossesRanked": 1,
    "division": "EE",
    "level": 362,
    "eloRanked": 1491,
    "eloChange": -18,
    "rankChange": -31,
    "wins": 0,
    "losses": 1,
    "rank": 43
  },
  {
    "id": 523755,
    "username": "jones69160",
    "winsRanked": 0,
    "lossesRanked": 1,
    "division": "EE",
    "level": 339,
    "eloRanked": 1490,
    "rank": 44
  },
  {
    "id": 390800,
    "username": "coolsanswitch",
    "winsRanked": 0,
    "lossesRanked": 1,
    "division": "EE",
    "level": 332,
    "eloRanked": 1490,
    "rank": 45
  },
  {
    "id": 571923,
    "username": "Doggo da artist",
    "winsRanked": 2,
    "lossesRanked": 0,
    "division": "E",
    "level": 684,
    "eloRanked": 1478,
    "rank": 46
  },
  {
    "id": 742306,
    "username": "Grtfj",
    "winsRanked": 1,
    "lossesRanked": 1,
    "division": "E",
    "level": 1039,
    "eloRanked": 1471,
    "rank": 47
  },
  {
    "id": 745352,
    "username": "Furiousbabytv",
    "winsRanked": 2,
    "lossesRanked": 1,
    "division": "E",
    "level": 220,
    "eloRanked": 1469,
    "rank": 48
  },
  {
    "id": 518759,
    "username": "zippet br",
    "winsRanked": 2,
    "lossesRanked": 2,
    "division": "E",
    "level": 390,
    "eloRanked": 1469,
    "rank": 49
  },
  {
    "id": 597045,
    "username": "3than",
    "winsRanked": 0,
    "lossesRanked": 1,
    "division": "E",
    "level": 553,
    "eloRanked": 1467,
    "rank": 50
  },
  {
    "id": 49044,
    "username": "netpet90",
    "winsRanked": 2,
    "lossesRanked": 2,
    "division": "E",
    "level": 434,
    "eloRanked": 1464,
    "rank": 51
  },
  {
    "id": 754135,
    "username": "YellowJack8",
    "winsRanked": 3,
    "lossesRanked": 1,
    "division": "E",
    "level": 189,
    "eloRanked": 1463,
    "eloChange": 24,
    "rankChange": -35,
    "wins": 1,
    "losses": 0,
    "rank": 52
  },
  {
    "id": 350751,
    "username": "Temmisgore",
    "winsRanked": 1,
    "lossesRanked": 1,
    "division": "E",
    "level": 302,
    "eloRanked": 1461,
    "eloChange": -22,
    "rankChange": -39,
    "wins": 0,
    "losses": 1,
    "rank": 53
  },
  {
    "id": 357950,
    "username": "Sonicgamer300",
    "winsRanked": 0,
    "lossesRanked": 1,
    "division": "E",
    "level": 1305,
    "eloRanked": 1460,
    "eloChange": 0,
    "rankChange": -39,
    "wins": 0,
    "losses": 0,
    "rank": 54
  },
  {
    "id": 381347,
    "username": "FeshoSamnapona",
    "winsRanked": 1,
    "lossesRanked": 0,
    "division": "FFF",
    "level": 295,
    "eloRanked": 1453,
    "eloChange": 0,
    "rankChange": -39,
    "wins": 0,
    "losses": 0,
    "rank": 55
  },
  {
    "id": 648671,
    "username": "Bruce Banner",
    "winsRanked": 1,
    "lossesRanked": 0,
    "division": "FFF",
    "level": 1050,
    "eloRanked": 1448,
    "rank": 56
  },
  {
    "id": 474026,
    "username": "Mettaton's Fan",
    "winsRanked": 1,
    "lossesRanked": 0,
    "division": "FFF",
    "level": 860,
    "eloRanked": 1447,
    "rank": 57
  },
  {
    "id": 757956,
    "username": "Sicking21",
    "winsRanked": 0,
    "lossesRanked": 2,
    "division": "FFF",
    "level": 425,
    "eloRanked": 1439,
    "rank": 58
  },
  {
    "id": 153099,
    "username": "Redskywalker29",
    "winsRanked": 1,
    "lossesRanked": 0,
    "division": "FFF",
    "level": 1091,
    "eloRanked": 1432,
    "rank": 59
  },
  {
    "id": 234406,
    "username": "JaCkAtTaCk",
    "winsRanked": 1,
    "lossesRanked": 0,
    "division": "FFF",
    "level": 226,
    "eloRanked": 1432,
    "rank": 60
  },
  {
    "id": 442901,
    "username": "DevilsLettuce48",
    "winsRanked": 1,
    "lossesRanked": 5,
    "division": "FFF",
    "level": 194,
    "eloRanked": 1430,
    "rank": 61
  },
  {
    "id": 743283,
    "username": "De Aster",
    "winsRanked": 0,
    "lossesRanked": 1,
    "division": "FFF",
    "level": 904,
    "eloRanked": 1430,
    "eloChange": 0,
    "rankChange": -44,
    "wins": 0,
    "losses": 0,
    "rank": 62
  },
  {
    "id": 200289,
    "username": "poiuytreza",
    "winsRanked": 0,
    "lossesRanked": 1,
    "division": "FFF",
    "level": 360,
    "eloRanked": 1430,
    "rank": 63
  },
  {
    "id": 377255,
    "username": "Juan123456",
    "winsRanked": 0,
    "lossesRanked": 1,
    "division": "FFF",
    "level": 347,
    "eloRanked": 1430,
    "eloChange": 0,
    "rankChange": -45,
    "wins": 0,
    "losses": 0,
    "rank": 64
  },
  {
    "id": 380256,
    "username": "Puppet_Gaming",
    "winsRanked": 0,
    "lossesRanked": 1,
    "division": "FFF",
    "level": 273,
    "eloRanked": 1430,
    "rank": 65
  },
  {
    "id": 1321,
    "username": "xX7679Xx",
    "winsRanked": 1,
    "lossesRanked": 0,
    "division": "FF",
    "level": 1204,
    "eloRanked": 1423,
    "eloChange": 0,
    "rankChange": -46,
    "wins": 0,
    "losses": 0,
    "rank": 66
  },
  {
    "id": 739588,
    "username": "Silverhorg",
    "winsRanked": 1,
    "lossesRanked": 1,
    "division": "FF",
    "level": 113,
    "eloRanked": 1416,
    "eloChange": 16,
    "rankChange": -44,
    "wins": 1,
    "losses": 0,
    "rank": 67
  },
  {
    "id": 769914,
    "username": "CosmicTheSquid",
    "winsRanked": 2,
    "lossesRanked": 3,
    "division": "FF",
    "level": 114,
    "eloRanked": 1412,
    "rank": 68
  },
  {
    "id": 170900,
    "username": "riolusx7",
    "winsRanked": 0,
    "lossesRanked": 1,
    "division": "FF",
    "level": 745,
    "eloRanked": 1408,
    "rank": 69
  },
  {
    "id": 107629,
    "username": "Apocalypse_now",
    "winsRanked": 2,
    "lossesRanked": 5,
    "division": "FF",
    "level": 737,
    "eloRanked": 1402,
    "rank": 70
  },
  {
    "id": 751115,
    "username": "Icysmiles",
    "winsRanked": 0,
    "lossesRanked": 1,
    "division": "FF",
    "level": 365,
    "eloRanked": 1400,
    "eloChange": 0,
    "rankChange": -49,
    "wins": 0,
    "losses": 0,
    "rank": 71
  },
  {
    "id": 385043,
    "username": "Nonikvanessa",
    "winsRanked": 1,
    "lossesRanked": 0,
    "division": "F",
    "level": 179,
    "eloRanked": 1396,
    "eloChange": 0,
    "rankChange": -48,
    "wins": 0,
    "losses": 0,
    "rank": 72
  },
  {
    "id": 771495,
    "username": "Silver_Starsong",
    "winsRanked": 3,
    "lossesRanked": 0,
    "division": "F",
    "level": 95,
    "eloRanked": 1392,
    "rank": 73
  },
  {
    "id": 775382,
    "username": "Say_Somethin",
    "winsRanked": 1,
    "lossesRanked": 0,
    "division": "F",
    "level": 61,
    "eloRanked": 1392,
    "eloChange": 0,
    "rankChange": -48,
    "wins": 0,
    "losses": 0,
    "rank": 74
  },
  {
    "id": 384970,
    "username": "Alezf",
    "winsRanked": 1,
    "lossesRanked": 0,
    "division": "F",
    "level": 332,
    "eloRanked": 1387,
    "rank": 75
  },
  {
    "id": 582954,
    "username": "puppet23",
    "winsRanked": 1,
    "lossesRanked": 0,
    "division": "F",
    "level": 62,
    "eloRanked": 1386,
    "rank": 76
  },
  {
    "id": 158856,
    "username": "Dovahkiin18",
    "winsRanked": 1,
    "lossesRanked": 0,
    "division": "F",
    "level": 333,
    "eloRanked": 1385,
    "rank": 77
  },
  {
    "id": 379114,
    "username": "Cally Whotsion",
    "winsRanked": 1,
    "lossesRanked": 0,
    "division": "F",
    "level": 240,
    "eloRanked": 1381,
    "rank": 78
  },
  {
    "id": 494708,
    "username": "Onlooker",
    "winsRanked": 0,
    "lossesRanked": 1,
    "division": "F",
    "level": 950,
    "eloRanked": 1378,
    "eloChange": 0,
    "rankChange": -52,
    "wins": 0,
    "losses": 0,
    "rank": 79
  },
  {
    "id": 675296,
    "username": "MeloWorld",
    "winsRanked": 2,
    "lossesRanked": 0,
    "division": "F",
    "level": 167,
    "eloRanked": 1377,
    "rank": 80
  },
  {
    "id": 198780,
    "username": "oshawott211",
    "winsRanked": 2,
    "lossesRanked": 1,
    "division": "F",
    "level": 250,
    "eloRanked": 1377,
    "rank": 81
  },
  {
    "id": 415380,
    "username": "Nirando",
    "winsRanked": 1,
    "lossesRanked": 1,
    "division": "F",
    "level": 576,
    "eloRanked": 1374,
    "eloChange": -19,
    "rankChange": -57,
    "wins": 0,
    "losses": 1,
    "rank": 82
  },
  {
    "id": 640611,
    "username": "The Mistress",
    "winsRanked": 0,
    "lossesRanked": 1,
    "division": "F",
    "level": 382,
    "eloRanked": 1370,
    "rank": 83
  },
  {
    "id": 372452,
    "username": "Matukas2",
    "winsRanked": 0,
    "lossesRanked": 1,
    "division": "F",
    "level": 329,
    "eloRanked": 1370,
    "eloChange": 0,
    "rankChange": -55,
    "wins": 0,
    "losses": 0,
    "rank": 84
  },
  {
    "id": 387433,
    "username": "Rubsy",
    "winsRanked": 0,
    "lossesRanked": 1,
    "division": "F",
    "level": 268,
    "eloRanked": 1370,
    "rank": 85
  },
  {
    "id": 764034,
    "username": "pollytheparrot",
    "winsRanked": 0,
    "lossesRanked": 3,
    "division": "F",
    "level": 143,
    "eloRanked": 1370,
    "rank": 86
  },
  {
    "id": 383039,
    "username": "Idoeoowiskskekw",
    "winsRanked": 1,
    "lossesRanked": 0,
    "division": "GGG",
    "level": 328,
    "eloRanked": 1364,
    "rank": 87
  },
  {
    "id": 762381,
    "username": "Pixie42",
    "winsRanked": 1,
    "lossesRanked": 0,
    "division": "GGG",
    "level": 122,
    "eloRanked": 1362,
    "eloChange": 0,
    "rankChange": -57,
    "wins": 0,
    "losses": 0,
    "rank": 88
  },
  {
    "id": 761404,
    "username": "Mad_Dummy10179",
    "winsRanked": 2,
    "lossesRanked": 0,
    "division": "GGG",
    "level": 47,
    "eloRanked": 1360,
    "eloChange": 19,
    "rankChange": -55,
    "wins": 1,
    "losses": 0,
    "rank": 89
  },
  {
    "id": 740495,
    "username": "Pokapy",
    "winsRanked": 0,
    "lossesRanked": 1,
    "division": "GGG",
    "level": 134,
    "eloRanked": 1355,
    "eloChange": 0,
    "rankChange": -58,
    "wins": 0,
    "losses": 0,
    "rank": 90
  },
  {
    "id": 763023,
    "username": "deceptor44",
    "winsRanked": 0,
    "lossesRanked": 6,
    "division": "GGG",
    "level": 514,
    "eloRanked": 1354,
    "eloChange": -55,
    "rankChange": -70,
    "wins": 0,
    "losses": 4,
    "rank": 91
  },
  {
    "id": 371783,
    "username": "NEON_Nick fox",
    "winsRanked": 1,
    "lossesRanked": 0,
    "division": "GGG",
    "level": 264,
    "eloRanked": 1350,
    "rank": 92
  },
  {
    "id": 165044,
    "username": "Frisk Kirisame",
    "winsRanked": 0,
    "lossesRanked": 2,
    "division": "GGG",
    "level": 745,
    "eloRanked": 1350,
    "eloChange": -20,
    "rankChange": -65,
    "wins": 0,
    "losses": 1,
    "rank": 93
  },
  {
    "id": 393954,
    "username": "Kenshinloria",
    "winsRanked": 0,
    "lossesRanked": 2,
    "division": "GGG",
    "level": 303,
    "eloRanked": 1347,
    "eloChange": -23,
    "rankChange": -64,
    "wins": 0,
    "losses": 1,
    "rank": 94
  },
  {
    "id": 586966,
    "username": "AkiraStrife",
    "winsRanked": 0,
    "lossesRanked": 1,
    "division": "GGG",
    "level": 558,
    "eloRanked": 1340,
    "eloChange": 0,
    "rankChange": -60,
    "wins": 0,
    "losses": 0,
    "rank": 95
  },
  {
    "id": 599970,
    "username": "Vizard",
    "winsRanked": 1,
    "lossesRanked": 0,
    "division": "GG",
    "level": 750,
    "eloRanked": 1323,
    "rank": 96
  },
  {
    "id": 617274,
    "username": "shadowbro4640",
    "winsRanked": 3,
    "lossesRanked": 0,
    "division": "GG",
    "level": 217,
    "eloRanked": 1322,
    "rank": 97
  },
  {
    "id": 430131,
    "username": "spnaonodpay",
    "winsRanked": 1,
    "lossesRanked": 3,
    "division": "GG",
    "level": 43,
    "eloRanked": 1322,
    "eloChange": -22,
    "rankChange": -65,
    "wins": 0,
    "losses": 2,
    "rank": 98
  },
  {
    "id": 776923,
    "username": "TeddyMass",
    "winsRanked": 1,
    "lossesRanked": 1,
    "division": "GG",
    "level": 37,
    "eloRanked": 1316,
    "rank": 99
  },
  {
    "id": 757037,
    "username": "ape0018",
    "winsRanked": 1,
    "lossesRanked": 3,
    "division": "GG",
    "level": 590,
    "eloRanked": 1316,
    "eloChange": 3,
    "rankChange": -64,
    "wins": 1,
    "losses": 2,
    "rank": 100
  },
  {
    "id": 593503,
    "username": "Stryker_",
    "winsRanked": 1,
    "lossesRanked": 2,
    "division": "GG",
    "level": 112,
    "eloRanked": 1312,
    "rank": 101
  },
  {
    "id": 750632,
    "username": "redwinter",
    "winsRanked": 0,
    "lossesRanked": 1,
    "division": "GG",
    "level": 24,
    "eloRanked": 1310,
    "rank": 102
  },
  {
    "id": 174948,
    "username": "ThatGuy0verSea",
    "winsRanked": 3,
    "lossesRanked": 0,
    "division": "G",
    "level": 91,
    "eloRanked": 1301,
    "eloChange": 48,
    "rankChange": -66,
    "wins": 2,
    "losses": 0,
    "rank": 103
  },
  {
    "id": 777907,
    "username": "floatiflame",
    "winsRanked": 2,
    "lossesRanked": 0,
    "division": "G",
    "level": 23,
    "eloRanked": 1298,
    "rank": 104
  },
  {
    "id": 233642,
    "username": "Cutiejackaboy",
    "winsRanked": 0,
    "lossesRanked": 2,
    "division": "G",
    "level": 127,
    "eloRanked": 1292,
    "rank": 105
  },
  {
    "id": 758914,
    "username": "DrybonesFan",
    "winsRanked": 1,
    "lossesRanked": 0,
    "division": "G",
    "level": 81,
    "eloRanked": 1285,
    "rank": 106
  },
  {
    "id": 774826,
    "username": "Bow_and_Arrow",
    "winsRanked": 1,
    "lossesRanked": 2,
    "division": "G",
    "level": 40,
    "eloRanked": 1283,
    "rank": 107
  },
  {
    "id": 777885,
    "username": "Ether5210",
    "winsRanked": 1,
    "lossesRanked": 0,
    "division": "HHH",
    "level": 29,
    "eloRanked": 1265,
    "rank": 108
  },
  {
    "id": 396202,
    "username": "COOLGUY29182",
    "winsRanked": 0,
    "lossesRanked": 1,
    "division": "HHH",
    "level": 221,
    "eloRanked": 1259,
    "rank": 109
  },
  {
    "id": 588089,
    "username": "LukeSky",
    "winsRanked": 0,
    "lossesRanked": 1,
    "division": "HHH",
    "level": 120,
    "eloRanked": 1250,
    "rank": 110
  },
  {
    "id": 774385,
    "username": "ViperMew",
    "winsRanked": 1,
    "lossesRanked": 0,
    "division": "HH",
    "level": 36,
    "eloRanked": 1246,
    "rank": 111
  },
  {
    "id": 575332,
    "username": "NyGame",
    "winsRanked": 0,
    "lossesRanked": 2,
    "division": "HH",
    "level": 38,
    "eloRanked": 1232,
    "rank": 112
  },
  {
    "id": 385142,
    "username": "Sans00121",
    "winsRanked": 0,
    "lossesRanked": 1,
    "division": "HH",
    "level": 274,
    "eloRanked": 1227,
    "rank": 113
  },
  {
    "id": 395312,
    "username": "jt979797",
    "winsRanked": 1,
    "lossesRanked": 0,
    "division": "HH",
    "level": 61,
    "eloRanked": 1226,
    "rank": 114
  },
  {
    "id": 114353,
    "username": "Nightmarespring",
    "winsRanked": 0,
    "lossesRanked": 1,
    "division": "HH",
    "level": 31,
    "eloRanked": 1221,
    "rank": 115
  },
  {
    "id": 427640,
    "username": "thesniperninja",
    "winsRanked": 0,
    "lossesRanked": 1,
    "division": "HH",
    "level": 169,
    "eloRanked": 1220,
    "rank": 116
  },
  {
    "id": 769231,
    "username": "PLANTIFERO",
    "winsRanked": 1,
    "lossesRanked": 0,
    "division": "ZZZ",
    "level": 4,
    "eloRanked": 1164,
    "rank": 117
  },
  {
    "id": 777891,
    "username": "Xelascorio",
    "winsRanked": 0,
    "lossesRanked": 1,
    "division": "Z",
    "level": 1,
    "eloRanked": 1100,
    "rank": 118
  }
]