[{"id":740957,"username":"wuvea","winsRanked":20,"lossesRanked":11,"division":"AA","level":1224,"eloRanked":1869,"eloChange":-158,"rankChange":21,"wins":-101,"losses":-66,"rank":1},{"id":778654,"username":"UTSPDRN","winsRanked":10,"lossesRanked":4,"division":"AA","level":100,"eloRanked":1852,"eloChange":-201,"rankChange":14,"wins":-165,"losses":-109,"rank":2},{"id":498412,"username":"LuckySpin","winsRanked":4,"lossesRanked":2,"division":"BBB","level":2026,"eloRanked":1804,"eloChange":-275,"rankChange":6,"wins":-110,"losses":-60,"rank":3},{"id":649454,"username":"DripDew","winsRanked":7,"lossesRanked":4,"division":"BBB","level":776,"eloRanked":1800,"eloChange":-293,"rankChange":2,"wins":-193,"losses":-122,"rank":4},{"id":777007,"username":"DeltaDr33murr","winsRanked":5,"lossesRanked":2,"division":"BB","level":430,"eloRanked":1786,"eloChange":-298,"rankChange":2,"wins":-242,"losses":-196,"rank":5},{"id":448883,"username":"XCriwn","winsRanked":10,"lossesRanked":7,"division":"BB","level":1962,"eloRanked":1768,"eloChange":-222,"rankChange":36,"wins":-147,"losses":-139,"rank":6},{"id":780263,"username":"GoodStatForCost","winsRanked":13,"lossesRanked":8,"division":"BB","level":68,"eloRanked":1765,"eloChange":-195,"rankChange":47,"wins":-90,"losses":-75,"rank":7},{"id":777992,"username":"Gott Ist Tout","winsRanked":8,"lossesRanked":3,"division":"BB","level":39,"eloRanked":1760,"eloChange":-181,"rankChange":58,"wins":-3,"losses":3,"rank":8},{"id":540690,"username":"poon","winsRanked":3,"lossesRanked":2,"division":"BB","level":2024,"eloRanked":1760,"eloChange":-313,"rankChange":4,"wins":-164,"losses":-106,"rank":9},{"id":775221,"username":"Lucyel","winsRanked":13,"lossesRanked":6,"division":"B","level":705,"eloRanked":1759,"eloChange":-142,"rankChange":83,"wins":-263,"losses":-289,"rank":10},{"id":207149,"username":"munhuu","winsRanked":1,"lossesRanked":0,"division":"B","level":949,"eloRanked":1753,"eloChange":-309,"rankChange":3,"wins":-139,"losses":-66,"rank":11},{"id":692766,"username":"evil netdecker","winsRanked":10,"lossesRanked":6,"division":"B","level":1027,"eloRanked":1748,"eloChange":-227,"rankChange":34,"wins":-275,"losses":-246,"rank":12},{"id":117850,"username":"bananacat50","winsRanked":19,"lossesRanked":13,"division":"B","level":392,"eloRanked":1745,"eloChange":-203,"rankChange":47,"wins":-264,"losses":-256,"rank":13},{"id":224611,"username":"´","winsRanked":14,"lossesRanked":7,"division":"B","level":1267,"eloRanked":1742,"eloChange":-67,"rankChange":163,"wins":-27,"losses":-32,"rank":14},{"id":770807,"username":"盛朵朵","winsRanked":4,"lossesRanked":3,"division":"B","level":258,"eloRanked":1737,"eloChange":-224,"rankChange":38,"wins":-54,"losses":-32,"rank":15},{"id":778392,"username":"Peppa Steak","winsRanked":3,"lossesRanked":2,"division":"B","level":35,"eloRanked":1736,"eloChange":-278,"rankChange":11,"wins":-11,"losses":2,"rank":16},{"id":692745,"username":"angelas37","winsRanked":8,"lossesRanked":6,"division":"B","level":2010,"eloRanked":1733,"eloChange":-287,"rankChange":7,"wins":-68,"losses":-46,"rank":17},{"id":759582,"username":"CoolDiamond123","winsRanked":8,"lossesRanked":4,"division":"B","level":829,"eloRanked":1732,"eloChange":-191,"rankChange":53,"wins":-40,"losses":-27,"rank":18},{"id":694036,"username":"Darkim27","winsRanked":0,"lossesRanked":1,"division":"B","level":1572,"eloRanked":1730,"eloChange":-330,"rankChange":-4,"wins":-80,"losses":-39,"rank":19},{"id":751350,"username":"rizzler","winsRanked":1,"lossesRanked":0,"division":"CCC","level":133,"eloRanked":1723,"eloChange":-279,"rankChange":16,"wins":-34,"losses":-10,"rank":20},{"id":453695,"username":"misterSD","winsRanked":23,"lossesRanked":20,"division":"CCC","level":2676,"eloRanked":1721,"eloChange":-172,"rankChange":78,"wins":-98,"losses":-86,"rank":21},{"id":665674,"username":"Crisptian","winsRanked":4,"lossesRanked":2,"division":"CCC","level":816,"eloRanked":1709,"rank":22},{"id":675980,"username":"bogdan98423498","winsRanked":21,"lossesRanked":14,"division":"CCC","level":984,"eloRanked":1709,"eloChange":31,"rankChange":296,"wins":-129,"losses":-173,"rank":23},{"id":779900,"username":"Hickey Mickey","winsRanked":10,"lossesRanked":1,"division":"CCC","level":22,"eloRanked":1708,"eloChange":36,"rankChange":303,"wins":3,"losses":-2,"rank":24},{"id":611082,"username":"Mustard","winsRanked":1,"lossesRanked":1,"division":"CCC","level":1304,"eloRanked":1705,"eloChange":-295,"rankChange":14,"wins":-69,"losses":-38,"rank":25},{"id":43414,"username":"StellarSting","winsRanked":3,"lossesRanked":2,"division":"CCC","level":549,"eloRanked":1702,"eloChange":-209,"rankChange":57,"wins":-156,"losses":-171,"rank":26},{"id":750704,"username":"unifoly","winsRanked":7,"lossesRanked":1,"division":"CCC","level":833,"eloRanked":1700,"eloChange":-60,"rankChange":199,"wins":-61,"losses":-65,"rank":27},{"id":524005,"username":"Kiwiz962","winsRanked":1,"lossesRanked":1,"division":"CCC","level":1237,"eloRanked":1700,"eloChange":-291,"rankChange":13,"wins":-87,"losses":-57,"rank":28},{"id":445423,"username":"RagedQuit","winsRanked":1,"lossesRanked":2,"division":"CCC","level":885,"eloRanked":1700,"eloChange":-307,"rankChange":4,"wins":-99,"losses":-76,"rank":29},{"id":488578,"username":"Inhale","winsRanked":0,"lossesRanked":1,"division":"CCC","level":1164,"eloRanked":1700,"eloChange":-328,"rankChange":-9,"wins":-80,"losses":-58,"rank":30},{"id":1385,"username":"alice,","winsRanked":2,"lossesRanked":1,"division":"CC","level":1316,"eloRanked":1699,"eloChange":-249,"rankChange":28,"wins":-85,"losses":-57,"rank":31},{"id":428886,"username":"Casdyne","winsRanked":8,"lossesRanked":1,"division":"CC","level":1223,"eloRanked":1695,"eloChange":-95,"rankChange":163,"wins":-91,"losses":-106,"rank":32},{"id":372074,"username":"godmano","winsRanked":6,"lossesRanked":5,"division":"CC","level":2106,"eloRanked":1679,"eloChange":-231,"rankChange":53,"wins":-99,"losses":-96,"rank":33},{"id":415713,"username":"ICanHasDorito","winsRanked":1,"lossesRanked":2,"division":"CC","level":1363,"eloRanked":1671,"eloChange":-330,"rankChange":3,"wins":-41,"losses":-14,"rank":34},{"id":777438,"username":"OXYGRN","winsRanked":2,"lossesRanked":1,"division":"CC","level":214,"eloRanked":1670,"eloChange":-232,"rankChange":56,"wins":-75,"losses":-73,"rank":35},{"id":706902,"username":"Bred","winsRanked":1,"lossesRanked":1,"division":"CC","level":1034,"eloRanked":1670,"eloChange":-265,"rankChange":33,"wins":-43,"losses":-20,"rank":36},{"id":156196,"username":"Gico","winsRanked":1,"lossesRanked":1,"division":"CC","level":472,"eloRanked":1670,"eloChange":-247,"rankChange":37,"wins":-88,"losses":-69,"rank":37},{"id":767235,"username":"ShadowFra_97","winsRanked":1,"lossesRanked":1,"division":"CC","level":126,"eloRanked":1670,"eloChange":-192,"rankChange":85,"wins":-108,"losses":-97,"rank":38},{"id":603854,"username":"Thundershade","winsRanked":10,"lossesRanked":10,"division":"CC","level":426,"eloRanked":1670,"eloChange":-224,"rankChange":59,"wins":-77,"losses":-53,"rank":39},{"id":419636,"username":"dolphinn","winsRanked":1,"lossesRanked":4,"division":"CC","level":854,"eloRanked":1670,"eloChange":-344,"rankChange":-12,"wins":-208,"losses":-200,"rank":40},{"id":778328,"username":"Cranberry Juice","winsRanked":2,"lossesRanked":1,"division":"C","level":33,"eloRanked":1660,"eloChange":-235,"rankChange":55,"wins":-16,"losses":-3,"rank":41},{"id":449939,"username":"XxmostafaxX123","winsRanked":4,"lossesRanked":4,"division":"C","level":647,"eloRanked":1660,"eloChange":-182,"rankChange":96,"wins":-66,"losses":-60,"rank":42},{"id":770255,"username":"Charist","winsRanked":4,"lossesRanked":6,"division":"C","level":453,"eloRanked":1660,"eloChange":-252,"rankChange":38,"wins":-68,"losses":-52,"rank":43},{"id":763728,"username":"Starster","winsRanked":4,"lossesRanked":2,"division":"C","level":443,"eloRanked":1659,"eloChange":-178,"rankChange":97,"wins":-88,"losses":-91,"rank":44},{"id":719356,"username":"EthanielGaming","winsRanked":7,"lossesRanked":6,"division":"C","level":1435,"eloRanked":1653,"eloChange":-153,"rankChange":135,"wins":-81,"losses":-84,"rank":45},{"id":761324,"username":"Fallen_Star","winsRanked":3,"lossesRanked":7,"division":"C","level":711,"eloRanked":1653,"eloChange":-398,"rankChange":-29,"wins":-160,"losses":-124,"rank":46},{"id":757410,"username":"Cirno","winsRanked":2,"lossesRanked":2,"division":"C","level":127,"eloRanked":1652,"eloChange":-234,"rankChange":56,"wins":-79,"losses":-59,"rank":47},{"id":567729,"username":"gamertime686","winsRanked":1,"lossesRanked":0,"division":"C","level":978,"eloRanked":1650,"eloChange":-240,"rankChange":53,"wins":-75,"losses":-58,"rank":48},{"id":474026,"username":"Mettaton's Fan","winsRanked":29,"lossesRanked":29,"division":"C","level":1089,"eloRanked":1646,"eloChange":-174,"rankChange":121,"wins":-235,"losses":-281,"rank":49},{"id":527016,"username":"Players","winsRanked":2,"lossesRanked":2,"division":"C","level":452,"eloRanked":1642,"eloChange":-238,"rankChange":60,"wins":-77,"losses":-67,"rank":50},{"id":426165,"username":"Best Basil","winsRanked":1,"lossesRanked":1,"division":"C","level":1471,"eloRanked":1640,"eloChange":-267,"rankChange":36,"wins":-99,"losses":-92,"rank":51},{"id":443865,"username":"Smartulu","winsRanked":1,"lossesRanked":2,"division":"C","level":382,"eloRanked":1640,"eloChange":-214,"rankChange":76,"wins":-84,"losses":-62,"rank":52},{"id":597289,"username":"IceNovice4163","winsRanked":7,"lossesRanked":4,"division":"DDD","level":1161,"eloRanked":1638,"eloChange":-119,"rankChange":177,"wins":-41,"losses":-26,"rank":53},{"id":13177,"username":"Jake Liberty","winsRanked":1,"lossesRanked":0,"division":"DDD","level":393,"eloRanked":1635,"eloChange":-65,"rankChange":234,"wins":-46,"losses":-41,"rank":54},{"id":80381,"username":"AngelGooey","winsRanked":6,"lossesRanked":7,"division":"DDD","level":305,"eloRanked":1630,"eloChange":-222,"rankChange":77,"wins":-112,"losses":-115,"rank":55},{"id":181453,"username":"GysLybitelBabys","winsRanked":2,"lossesRanked":4,"division":"DDD","level":652,"eloRanked":1627,"eloChange":-295,"rankChange":17,"wins":-20,"losses":-10,"rank":56},{"id":262033,"username":"ethannoodle","winsRanked":5,"lossesRanked":6,"division":"DDD","level":769,"eloRanked":1626,"eloChange":-171,"rankChange":131,"wins":-77,"losses":-70,"rank":57},{"id":119383,"username":"OWENFACE","winsRanked":2,"lossesRanked":0,"division":"DDD","level":603,"eloRanked":1625,"eloChange":-195,"rankChange":106,"wins":-52,"losses":-36,"rank":58},{"id":93452,"username":"GamingToTheMax","winsRanked":2,"lossesRanked":4,"division":"DDD","level":3714,"eloRanked":1624,"eloChange":-322,"rankChange":3,"wins":-329,"losses":-352,"rank":59},{"id":741766,"username":"JaimeezNuts","winsRanked":1,"lossesRanked":0,"division":"DDD","level":502,"eloRanked":1622,"eloChange":-231,"rankChange":70,"wins":-32,"losses":-21,"rank":60},{"id":774369,"username":"PowerKreep","winsRanked":2,"lossesRanked":0,"division":"DDD","level":359,"eloRanked":1620,"eloChange":-201,"rankChange":100,"wins":-115,"losses":-130,"rank":61},{"id":637806,"username":"Thunm","winsRanked":1,"lossesRanked":0,"division":"DDD","level":241,"eloRanked":1620,"eloChange":-41,"rankChange":297,"wins":-147,"losses":-166,"rank":62},{"id":773712,"username":"xdvarcy","winsRanked":2,"lossesRanked":0,"division":"DDD","level":287,"eloRanked":1619,"eloChange":-211,"rankChange":83,"wins":-82,"losses":-79,"rank":63},{"id":66304,"username":"GabrilmanX","winsRanked":3,"lossesRanked":0,"division":"DDD","level":2568,"eloRanked":1617,"eloChange":9,"rankChange":413,"wins":-70,"losses":-90,"rank":64},{"id":428887,"username":"Nekoluga","winsRanked":4,"lossesRanked":1,"division":"DDD","level":539,"eloRanked":1611,"eloChange":-150,"rankChange":154,"wins":-60,"losses":-59,"rank":65},{"id":418970,"username":"LunarBlueberry","winsRanked":4,"lossesRanked":3,"division":"DDD","level":934,"eloRanked":1610,"eloChange":-202,"rankChange":109,"wins":-82,"losses":-89,"rank":66},{"id":433216,"username":"AG","winsRanked":3,"lossesRanked":6,"division":"DDD","level":2430,"eloRanked":1610,"eloChange":-316,"rankChange":3,"wins":-132,"losses":-125,"rank":67},{"id":241865,"username":"TrueTitan14","winsRanked":0,"lossesRanked":5,"division":"DDD","level":450,"eloRanked":1610,"eloChange":-354,"rankChange":-17,"wins":-190,"losses":-186,"rank":68},{"id":778891,"username":"player104","winsRanked":2,"lossesRanked":0,"division":"DD","level":247,"eloRanked":1609,"eloChange":-211,"rankChange":98,"wins":-129,"losses":-123,"rank":69},{"id":778417,"username":"Wassup My Rigor","winsRanked":1,"lossesRanked":0,"division":"DD","level":36,"eloRanked":1609,"eloChange":-220,"rankChange":78,"wins":-17,"losses":-5,"rank":70},{"id":157096,"username":"Homem Mascarado","winsRanked":9,"lossesRanked":4,"division":"DD","level":1151,"eloRanked":1609,"eloChange":-77,"rankChange":233,"wins":-227,"losses":-278,"rank":71},{"id":633601,"username":"taro","winsRanked":3,"lossesRanked":4,"division":"DD","level":322,"eloRanked":1608,"eloChange":-219,"rankChange":81,"wins":-99,"losses":-89,"rank":72},{"id":85557,"username":"Reaper!Sans","winsRanked":1,"lossesRanked":0,"division":"DD","level":453,"eloRanked":1606,"eloChange":-179,"rankChange":125,"wins":-58,"losses":-49,"rank":73},{"id":775980,"username":"Francix","winsRanked":2,"lossesRanked":0,"division":"DD","level":170,"eloRanked":1598,"eloChange":-210,"rankChange":105,"wins":-51,"losses":-51,"rank":74},{"id":426747,"username":"anthoneyo","winsRanked":2,"lossesRanked":2,"division":"DD","level":701,"eloRanked":1590,"eloChange":-230,"rankChange":91,"wins":-74,"losses":-69,"rank":75},{"id":370081,"username":"Demon Divergent","winsRanked":10,"lossesRanked":22,"division":"DD","level":5496,"eloRanked":1590,"eloChange":-421,"rankChange":-46,"wins":-91,"losses":-62,"rank":76},{"id":445173,"username":"FluffyBunCake","winsRanked":6,"lossesRanked":7,"division":"DD","level":489,"eloRanked":1587,"eloChange":-162,"rankChange":155,"wins":-46,"losses":-27,"rank":77},{"id":722146,"username":"Xackii","winsRanked":4,"lossesRanked":4,"division":"DD","level":512,"eloRanked":1584,"eloChange":-296,"rankChange":33,"wins":-120,"losses":-112,"rank":78},{"id":174294,"username":"Dylan Hall","winsRanked":1,"lossesRanked":2,"division":"DD","level":1758,"eloRanked":1584,"eloChange":-287,"rankChange":39,"wins":-39,"losses":-29,"rank":79},{"id":625465,"username":"marx109","winsRanked":1,"lossesRanked":3,"division":"DD","level":891,"eloRanked":1584,"eloChange":-282,"rankChange":41,"wins":-33,"losses":-13,"rank":80},{"id":723433,"username":"Peachysakura","winsRanked":2,"lossesRanked":2,"division":"DD","level":737,"eloRanked":1582,"eloChange":-230,"rankChange":93,"wins":-78,"losses":-72,"rank":81},{"id":596051,"username":"Vanopolo","winsRanked":0,"lossesRanked":5,"division":"DD","level":515,"eloRanked":1581,"eloChange":-293,"rankChange":32,"wins":-82,"losses":-82,"rank":82},{"id":254207,"username":"MadJester98","winsRanked":1,"lossesRanked":1,"division":"DD","level":761,"eloRanked":1580,"eloChange":-150,"rankChange":178,"wins":-129,"losses":-150,"rank":83},{"id":587799,"username":"JustAnUndertale","winsRanked":3,"lossesRanked":4,"division":"DD","level":329,"eloRanked":1580,"eloChange":-210,"rankChange":110,"wins":-198,"losses":-210,"rank":84},{"id":756342,"username":"#1 GERSON FAN!!","winsRanked":0,"lossesRanked":3,"division":"DD","level":414,"eloRanked":1580,"eloChange":-281,"rankChange":39,"wins":-30,"losses":-7,"rank":85},{"id":427561,"username":"Martlet Enjoyer","winsRanked":3,"lossesRanked":3,"division":"D","level":334,"eloRanked":1575,"eloChange":-245,"rankChange":77,"wins":-50,"losses":-30,"rank":86},{"id":650313,"username":"Askz","winsRanked":3,"lossesRanked":16,"division":"D","level":2396,"eloRanked":1572,"eloChange":-413,"rankChange":-43,"wins":-220,"losses":-211,"rank":87},{"id":359097,"username":"Nersuna","winsRanked":0,"lossesRanked":1,"division":"D","level":1932,"eloRanked":1561,"eloChange":-265,"rankChange":66,"wins":-163,"losses":-180,"rank":88},{"id":221160,"username":"Destroyer2726q2","winsRanked":1,"lossesRanked":0,"division":"D","level":544,"eloRanked":1553,"eloChange":-207,"rankChange":138,"wins":-101,"losses":-106,"rank":89},{"id":762255,"username":"zumerit","winsRanked":3,"lossesRanked":2,"division":"D","level":348,"eloRanked":1550,"eloChange":-235,"rankChange":109,"wins":-127,"losses":-144,"rank":90},{"id":779700,"username":"Osee Dee","winsRanked":1,"lossesRanked":1,"division":"D","level":132,"eloRanked":1550,"eloChange":-210,"rankChange":137,"wins":-124,"losses":-131,"rank":91},{"id":650548,"username":"SussyBaka?","winsRanked":10,"lossesRanked":10,"division":"D","level":163,"eloRanked":1550,"eloChange":47,"rankChange":635,"wins":-27,"losses":-48,"rank":92},{"id":388904,"username":"BossBryce39","winsRanked":0,"lossesRanked":1,"division":"D","level":498,"eloRanked":1550,"eloChange":-243,"rankChange":96,"wins":-60,"losses":-47,"rank":93},{"id":667069,"username":"-Vessel-","winsRanked":1,"lossesRanked":1,"division":"EEE","level":851,"eloRanked":1548,"eloChange":-222,"rankChange":121,"wins":-92,"losses":-94,"rank":94},{"id":762663,"username":"elNaight","winsRanked":3,"lossesRanked":1,"division":"EEE","level":414,"eloRanked":1545,"eloChange":-127,"rankChange":235,"wins":-61,"losses":-75,"rank":95},{"id":381138,"username":"Jakkapat02","winsRanked":9,"lossesRanked":7,"division":"EEE","level":251,"eloRanked":1543,"eloChange":-117,"rankChange":265,"wins":-91,"losses":-96,"rank":96},{"id":778046,"username":"GowGow","winsRanked":2,"lossesRanked":2,"division":"EEE","level":205,"eloRanked":1543,"rank":97},{"id":772156,"username":"red nut ale","winsRanked":5,"lossesRanked":1,"division":"EEE","level":285,"eloRanked":1539,"eloChange":-91,"rankChange":341,"wins":-37,"losses":-51,"rank":98},{"id":390615,"username":"TheLudicrousLuv","winsRanked":3,"lossesRanked":5,"division":"EEE","level":1396,"eloRanked":1539,"eloChange":-240,"rankChange":105,"wins":-133,"losses":-129,"rank":99},{"id":73486,"username":"StarshipInkling","winsRanked":1,"lossesRanked":0,"division":"EEE","level":250,"eloRanked":1537,"eloChange":-237,"rankChange":111,"wins":-100,"losses":-100,"rank":100},{"id":380305,"username":"Vandan","winsRanked":1,"lossesRanked":1,"division":"EEE","level":416,"eloRanked":1536,"eloChange":-246,"rankChange":101,"wins":-48,"losses":-43,"rank":101},{"id":421069,"username":"whenyoucando","winsRanked":1,"lossesRanked":1,"division":"EEE","level":2073,"eloRanked":1535,"eloChange":-195,"rankChange":157,"wins":-104,"losses":-113,"rank":102},{"id":757222,"username":"BPB_Games","winsRanked":2,"lossesRanked":1,"division":"EEE","level":172,"eloRanked":1534,"eloChange":-125,"rankChange":260,"wins":-50,"losses":-29,"rank":103},{"id":770408,"username":"CocoH","winsRanked":2,"lossesRanked":0,"division":"EEE","level":180,"eloRanked":1533,"eloChange":-154,"rankChange":197,"wins":-34,"losses":-28,"rank":104},{"id":393504,"username":"jeremiaspro300","winsRanked":3,"lossesRanked":1,"division":"EEE","level":353,"eloRanked":1532,"eloChange":-128,"rankChange":257,"wins":-47,"losses":-52,"rank":105},{"id":674249,"username":"windows97","winsRanked":3,"lossesRanked":1,"division":"EEE","level":125,"eloRanked":1527,"eloChange":-132,"rankChange":258,"wins":-98,"losses":-119,"rank":106},{"id":593406,"username":"Chtony","winsRanked":2,"lossesRanked":1,"division":"EEE","level":86,"eloRanked":1527,"eloChange":-83,"rankChange":365,"wins":-21,"losses":-19,"rank":107},{"id":523476,"username":"MPR27","winsRanked":4,"lossesRanked":3,"division":"EEE","level":69,"eloRanked":1527,"eloChange":-173,"rankChange":179,"wins":-27,"losses":-18,"rank":108},{"id":29477,"username":"ChezDeFez","winsRanked":5,"lossesRanked":10,"division":"EEE","level":299,"eloRanked":1525,"eloChange":-159,"rankChange":198,"wins":-100,"losses":-107,"rank":109},{"id":750191,"username":"Torchthe62nd","winsRanked":2,"lossesRanked":5,"division":"EEE","level":319,"eloRanked":1521,"eloChange":-137,"rankChange":258,"wins":-101,"losses":-111,"rank":110},{"id":392701,"username":"kill me pls","winsRanked":2,"lossesRanked":1,"division":"EEE","level":393,"eloRanked":1520,"eloChange":-113,"rankChange":322,"wins":-53,"losses":-49,"rank":111},{"id":773346,"username":"Phantom64","winsRanked":5,"lossesRanked":4,"division":"EEE","level":106,"eloRanked":1520,"eloChange":-22,"rankChange":503,"wins":-40,"losses":-41,"rank":112},{"id":662773,"username":"Dnom","winsRanked":1,"lossesRanked":2,"division":"EEE","level":949,"eloRanked":1520,"eloChange":-122,"rankChange":303,"wins":-114,"losses":-133,"rank":113},{"id":29091,"username":"DerpDerpson","winsRanked":0,"lossesRanked":1,"division":"EEE","level":1657,"eloRanked":1520,"eloChange":-135,"rankChange":263,"wins":-61,"losses":-58,"rank":114},{"id":748420,"username":"richardrich100","winsRanked":1,"lossesRanked":0,"division":"EE","level":214,"eloRanked":1518,"eloChange":-23,"rankChange":502,"wins":-4,"losses":-1,"rank":115},{"id":336637,"username":"Ghost2772","winsRanked":1,"lossesRanked":0,"division":"EE","level":678,"eloRanked":1515,"eloChange":-111,"rankChange":325,"wins":-13,"losses":-4,"rank":116},{"id":772374,"username":"SansBello","winsRanked":7,"lossesRanked":9,"division":"EE","level":67,"eloRanked":1513,"eloChange":-7,"rankChange":564,"wins":-48,"losses":-44,"rank":117},{"id":383042,"username":"Screembo","winsRanked":1,"lossesRanked":1,"division":"EE","level":321,"eloRanked":1508,"eloChange":-180,"rankChange":181,"wins":-56,"losses":-50,"rank":118},{"id":379828,"username":"weirdo","winsRanked":0,"lossesRanked":1,"division":"EE","level":385,"eloRanked":1508,"eloChange":-252,"rankChange":106,"wins":-48,"losses":-43,"rank":119},{"id":390079,"username":"meatyeggroll","winsRanked":3,"lossesRanked":1,"division":"EE","level":431,"eloRanked":1506,"eloChange":-74,"rankChange":408,"wins":-52,"losses":-48,"rank":120},{"id":215369,"username":"Genocide_Games","winsRanked":10,"lossesRanked":7,"division":"EE","level":671,"eloRanked":1506,"eloChange":-141,"rankChange":278,"wins":-180,"losses":-224,"rank":121},{"id":768667,"username":"Logiebear","winsRanked":0,"lossesRanked":1,"division":"EE","level":167,"eloRanked":1505,"eloChange":-136,"rankChange":300,"wins":-105,"losses":-109,"rank":122},{"id":628216,"username":"Gaziki","winsRanked":3,"lossesRanked":5,"division":"EE","level":391,"eloRanked":1503,"eloChange":-202,"rankChange":161,"wins":-51,"losses":-58,"rank":123},{"id":481679,"username":"clpb","winsRanked":0,"lossesRanked":2,"division":"EE","level":600,"eloRanked":1501,"eloChange":-229,"rankChange":133,"wins":-19,"losses":-12,"rank":124},{"id":373251,"username":"Blate","winsRanked":1,"lossesRanked":0,"division":"EE","level":391,"eloRanked":1500,"eloChange":-128,"rankChange":315,"wins":-47,"losses":-54,"rank":125},{"id":108160,"username":"Domi812","winsRanked":3,"lossesRanked":0,"division":"EE","level":1198,"eloRanked":1499,"eloChange":-103,"rankChange":359,"wins":-28,"losses":-24,"rank":126},{"id":778226,"username":"toetickler12","winsRanked":3,"lossesRanked":2,"division":"EE","level":143,"eloRanked":1497,"eloChange":-173,"rankChange":217,"wins":-77,"losses":-82,"rank":127},{"id":153411,"username":"SkullTH655","winsRanked":3,"lossesRanked":6,"division":"EE","level":1287,"eloRanked":1497,"eloChange":-237,"rankChange":125,"wins":-29,"losses":-16,"rank":128},{"id":264227,"username":"Sansssss","winsRanked":1,"lossesRanked":0,"division":"EE","level":358,"eloRanked":1494,"eloChange":-176,"rankChange":204,"wins":-42,"losses":-20,"rank":129},{"id":384809,"username":"momoX0809","winsRanked":0,"lossesRanked":3,"division":"EE","level":418,"eloRanked":1494,"eloChange":-195,"rankChange":167,"wins":-51,"losses":-44,"rank":130},{"id":773210,"username":"m6135r","winsRanked":1,"lossesRanked":2,"division":"EE","level":257,"eloRanked":1493,"eloChange":-244,"rankChange":117,"wins":-61,"losses":-51,"rank":131},{"id":773298,"username":"CorgiMaster007","winsRanked":1,"lossesRanked":0,"division":"EE","level":233,"eloRanked":1492,"eloChange":-169,"rankChange":226,"wins":-57,"losses":-58,"rank":132},{"id":381395,"username":"aasadasadas","winsRanked":1,"lossesRanked":1,"division":"EE","level":391,"eloRanked":1492,"eloChange":-173,"rankChange":215,"wins":-52,"losses":-46,"rank":133},{"id":142844,"username":"Essisten","winsRanked":5,"lossesRanked":8,"division":"EE","level":1050,"eloRanked":1492,"eloChange":-237,"rankChange":128,"wins":-160,"losses":-177,"rank":134},{"id":780250,"username":"RBF Syndrome","winsRanked":1,"lossesRanked":1,"division":"EE","level":12,"eloRanked":1490,"eloChange":-195,"rankChange":170,"wins":-24,"losses":-2,"rank":135},{"id":641206,"username":"Blaze Dragothan","winsRanked":4,"lossesRanked":4,"division":"EE","level":939,"eloRanked":1490,"eloChange":-122,"rankChange":330,"wins":-13,"losses":-10,"rank":136},{"id":648671,"username":"Bruce Banner","winsRanked":0,"lossesRanked":1,"division":"EE","level":1138,"eloRanked":1490,"eloChange":-237,"rankChange":126,"wins":-100,"losses":-110,"rank":137},{"id":399888,"username":"Peethegamer","winsRanked":1,"lossesRanked":0,"division":"E","level":355,"eloRanked":1484,"eloChange":-156,"rankChange":288,"wins":-51,"losses":-48,"rank":138},{"id":749940,"username":"Chessplayer NEO","winsRanked":1,"lossesRanked":1,"division":"E","level":405,"eloRanked":1484,"rank":139},{"id":395322,"username":"GalacticNova99","winsRanked":1,"lossesRanked":0,"division":"E","level":427,"eloRanked":1482,"eloChange":-174,"rankChange":233,"wins":-48,"losses":-51,"rank":140},{"id":379141,"username":"RAINBOW GHASTER","winsRanked":1,"lossesRanked":2,"division":"E","level":357,"eloRanked":1482,"eloChange":-197,"rankChange":175,"wins":-52,"losses":-44,"rank":141},{"id":121335,"username":"shadowdragon216","winsRanked":2,"lossesRanked":0,"division":"E","level":2154,"eloRanked":1480,"eloChange":-134,"rankChange":321,"wins":-68,"losses":-80,"rank":142},{"id":337342,"username":"RizekC","winsRanked":1,"lossesRanked":0,"division":"E","level":191,"eloRanked":1480,"eloChange":-153,"rankChange":291,"wins":-101,"losses":-114,"rank":143},{"id":119815,"username":"Nouch","winsRanked":1,"lossesRanked":0,"division":"E","level":187,"eloRanked":1479,"eloChange":40,"rankChange":808,"wins":-13,"losses":-8,"rank":144},{"id":381347,"username":"FeshoSamnapona","winsRanked":1,"lossesRanked":2,"division":"E","level":405,"eloRanked":1479,"eloChange":-171,"rankChange":248,"wins":-52,"losses":-52,"rank":145},{"id":402641,"username":"Kaori,,","winsRanked":3,"lossesRanked":10,"division":"E","level":439,"eloRanked":1479,"eloChange":-115,"rankChange":351,"wins":-132,"losses":-158,"rank":146},{"id":46985,"username":"foreverafter","winsRanked":2,"lossesRanked":1,"division":"E","level":446,"eloRanked":1478,"eloChange":-142,"rankChange":304,"wins":-12,"losses":0,"rank":147},{"id":561746,"username":"Zfriend456","winsRanked":2,"lossesRanked":2,"division":"E","level":543,"eloRanked":1476,"eloChange":-205,"rankChange":163,"wins":-75,"losses":-92,"rank":148},{"id":632289,"username":"Guará","winsRanked":0,"lossesRanked":2,"division":"E","level":646,"eloRanked":1475,"eloChange":-267,"rankChange":88,"wins":-237,"losses":-275,"rank":149},{"id":775947,"username":"gustergusterov","winsRanked":0,"lossesRanked":2,"division":"E","level":280,"eloRanked":1475,"eloChange":-198,"rankChange":174,"wins":-74,"losses":-91,"rank":150},{"id":779294,"username":"Entername0916","winsRanked":1,"lossesRanked":1,"division":"E","level":108,"eloRanked":1474,"eloChange":-157,"rankChange":287,"wins":-112,"losses":-115,"rank":151},{"id":554967,"username":"zuperdooper","winsRanked":4,"lossesRanked":2,"division":"E","level":96,"eloRanked":1472,"eloChange":-117,"rankChange":354,"wins":-34,"losses":-22,"rank":152},{"id":441474,"username":"erdemmer","winsRanked":0,"lossesRanked":2,"division":"E","level":940,"eloRanked":1472,"eloChange":-245,"rankChange":124,"wins":-146,"losses":-154,"rank":153},{"id":306310,"username":"Bokyubi","winsRanked":2,"lossesRanked":3,"division":"E","level":1086,"eloRanked":1470,"eloChange":-191,"rankChange":202,"wins":-17,"losses":-13,"rank":154},{"id":610710,"username":"Doctor Worm","winsRanked":4,"lossesRanked":0,"division":"E","level":567,"eloRanked":1467,"eloChange":-46,"rankChange":547,"wins":-2,"losses":-14,"rank":155},{"id":383822,"username":"staryack","winsRanked":2,"lossesRanked":2,"division":"E","level":388,"eloRanked":1464,"eloChange":-158,"rankChange":292,"wins":-55,"losses":-60,"rank":156},{"id":655053,"username":"rereretwoto","winsRanked":2,"lossesRanked":3,"division":"E","level":401,"eloRanked":1464,"eloChange":-192,"rankChange":215,"wins":-43,"losses":-34,"rank":157},{"id":390976,"username":"Zeyroner","winsRanked":1,"lossesRanked":2,"division":"E","level":342,"eloRanked":1464,"eloChange":-189,"rankChange":225,"wins":-51,"losses":-50,"rank":158},{"id":399927,"username":"EpicYoloSans","winsRanked":1,"lossesRanked":0,"division":"E","level":451,"eloRanked":1463,"eloChange":-110,"rankChange":377,"wins":-46,"losses":-47,"rank":159},{"id":779746,"username":"mar6969","winsRanked":5,"lossesRanked":2,"division":"E","level":146,"eloRanked":1462,"eloChange":-58,"rankChange":526,"wins":-140,"losses":-190,"rank":160},{"id":379417,"username":"Mattikiller","winsRanked":1,"lossesRanked":1,"division":"E","level":414,"eloRanked":1462,"eloChange":-174,"rankChange":269,"wins":-52,"losses":-48,"rank":161},{"id":30803,"username":"Manic_Malf","winsRanked":6,"lossesRanked":9,"division":"E","level":316,"eloRanked":1462,"eloChange":-199,"rankChange":198,"wins":-113,"losses":-146,"rank":162},{"id":153906,"username":"Brohamz12","winsRanked":0,"lossesRanked":1,"division":"E","level":347,"eloRanked":1462,"rank":163},{"id":521432,"username":"Papyrus3312","winsRanked":3,"lossesRanked":2,"division":"E","level":271,"eloRanked":1460,"eloChange":-103,"rankChange":398,"wins":-32,"losses":-34,"rank":164},{"id":650763,"username":"StarFellow23","winsRanked":1,"lossesRanked":1,"division":"E","level":844,"eloRanked":1460,"eloChange":-171,"rankChange":271,"wins":-6,"losses":-1,"rank":165},{"id":385604,"username":"itsme468","winsRanked":1,"lossesRanked":2,"division":"E","level":408,"eloRanked":1460,"eloChange":-180,"rankChange":261,"wins":-51,"losses":-50,"rank":166},{"id":720659,"username":"Void866","winsRanked":1,"lossesRanked":3,"division":"E","level":301,"eloRanked":1460,"eloChange":-143,"rankChange":316,"wins":-86,"losses":-102,"rank":167},{"id":780251,"username":"Bitch Hormones","winsRanked":0,"lossesRanked":1,"division":"E","level":14,"eloRanked":1460,"eloChange":-185,"rankChange":237,"wins":-30,"losses":-8,"rank":168},{"id":641554,"username":"124","winsRanked":4,"lossesRanked":0,"division":"FFF","level":571,"eloRanked":1459,"eloChange":53,"rankChange":893,"wins":-116,"losses":-155,"rank":169},{"id":380885,"username":"Omega Sans X3","winsRanked":2,"lossesRanked":0,"division":"FFF","level":421,"eloRanked":1459,"eloChange":-75,"rankChange":468,"wins":-58,"losses":-63,"rank":170},{"id":393242,"username":"QuindimBR","winsRanked":2,"lossesRanked":0,"division":"FFF","level":417,"eloRanked":1458,"eloChange":-101,"rankChange":403,"wins":-53,"losses":-52,"rank":171},{"id":377255,"username":"Juan123456","winsRanked":3,"lossesRanked":0,"division":"FFF","level":449,"eloRanked":1447,"eloChange":-34,"rankChange":627,"wins":-45,"losses":-61,"rank":172},{"id":774138,"username":"waycalm","winsRanked":4,"lossesRanked":1,"division":"FFF","level":181,"eloRanked":1446,"eloChange":-44,"rankChange":600,"wins":-42,"losses":-45,"rank":173},{"id":748184,"username":"koala_wow","winsRanked":1,"lossesRanked":3,"division":"FFF","level":798,"eloRanked":1446,"eloChange":-148,"rankChange":324,"wins":-149,"losses":-184,"rank":174},{"id":381993,"username":"JT Gerdes","winsRanked":0,"lossesRanked":2,"division":"FFF","level":344,"eloRanked":1446,"eloChange":-202,"rankChange":222,"wins":-51,"losses":-51,"rank":175},{"id":17915,"username":"IlovZombieBuffa","winsRanked":3,"lossesRanked":3,"division":"FFF","level":1458,"eloRanked":1445,"eloChange":-8,"rankChange":724,"wins":-161,"losses":-211,"rank":176},{"id":758890,"username":"charmtry","winsRanked":7,"lossesRanked":16,"division":"FFF","level":724,"eloRanked":1437,"eloChange":-245,"rankChange":132,"wins":-198,"losses":-230,"rank":177},{"id":390800,"username":"coolsanswitch","winsRanked":2,"lossesRanked":3,"division":"FFF","level":430,"eloRanked":1435,"eloChange":-184,"rankChange":276,"wins":-43,"losses":-49,"rank":178},{"id":381359,"username":"Sans8283738","winsRanked":1,"lossesRanked":2,"division":"FFF","level":353,"eloRanked":1432,"eloChange":-163,"rankChange":314,"wins":-49,"losses":-49,"rank":179},{"id":452130,"username":"CC-4147","winsRanked":1,"lossesRanked":1,"division":"FFF","level":968,"eloRanked":1431,"eloChange":-156,"rankChange":331,"wins":-24,"losses":-16,"rank":180},{"id":761770,"username":"roguestar23","winsRanked":9,"lossesRanked":4,"division":"FFF","level":216,"eloRanked":1430,"eloChange":-34,"rankChange":677,"wins":-81,"losses":-127,"rank":181},{"id":779825,"username":"LordAnomaly666","winsRanked":3,"lossesRanked":2,"division":"FFF","level":129,"eloRanked":1430,"eloChange":-181,"rankChange":287,"wins":-207,"losses":-261,"rank":182},{"id":519840,"username":"Noob_Player","winsRanked":3,"lossesRanked":3,"division":"FFF","level":594,"eloRanked":1430,"eloChange":-155,"rankChange":329,"wins":-8,"losses":-6,"rank":183},{"id":383669,"username":"ClassicBerry","winsRanked":0,"lossesRanked":1,"division":"FFF","level":391,"eloRanked":1430,"eloChange":-152,"rankChange":336,"wins":-50,"losses":-45,"rank":184},{"id":517619,"username":"mattwantcards","winsRanked":0,"lossesRanked":1,"division":"FFF","level":205,"eloRanked":1430,"eloChange":-99,"rankChange":466,"wins":-14,"losses":-13,"rank":185},{"id":397293,"username":"maksimus","winsRanked":1,"lossesRanked":0,"division":"FF","level":346,"eloRanked":1429,"eloChange":-114,"rankChange":426,"wins":-51,"losses":-48,"rank":186},{"id":393530,"username":"Shinok","winsRanked":1,"lossesRanked":1,"division":"FF","level":366,"eloRanked":1429,"eloChange":-162,"rankChange":317,"wins":-43,"losses":-44,"rank":187},{"id":387732,"username":"sansj3412","winsRanked":2,"lossesRanked":0,"division":"FF","level":401,"eloRanked":1427,"eloChange":-93,"rankChange":496,"wins":-49,"losses":-58,"rank":188},{"id":391347,"username":"foxtrot1422","winsRanked":1,"lossesRanked":0,"division":"FF","level":408,"eloRanked":1426,"eloChange":-124,"rankChange":410,"wins":-54,"losses":-56,"rank":189},{"id":209152,"username":"Lurker","winsRanked":1,"lossesRanked":0,"division":"FF","level":1421,"eloRanked":1425,"eloChange":-144,"rankChange":357,"wins":-16,"losses":-22,"rank":190},{"id":720046,"username":"a_random_person","winsRanked":1,"lossesRanked":1,"division":"FF","level":444,"eloRanked":1424,"eloChange":-138,"rankChange":372,"wins":-10,"losses":-4,"rank":191},{"id":381452,"username":"adzn","winsRanked":1,"lossesRanked":0,"division":"FF","level":325,"eloRanked":1422,"eloChange":-122,"rankChange":419,"wins":-52,"losses":-53,"rank":192},{"id":749998,"username":"dev!ant","winsRanked":12,"lossesRanked":4,"division":"FF","level":42,"eloRanked":1420,"eloChange":89,"rankChange":1173,"wins":-18,"losses":-28,"rank":193},{"id":396596,"username":"KirbyGamerYT","winsRanked":1,"lossesRanked":1,"division":"FF","level":439,"eloRanked":1420,"eloChange":-133,"rankChange":390,"wins":-40,"losses":-39,"rank":194},{"id":164870,"username":"Jalapenos78","winsRanked":13,"lossesRanked":20,"division":"FF","level":1068,"eloRanked":1420,"rank":195},{"id":754135,"username":"YellowJack8","winsRanked":3,"lossesRanked":0,"division":"FF","level":216,"eloRanked":1416,"eloChange":-88,"rankChange":529,"wins":-18,"losses":-15,"rank":196},{"id":777837,"username":"GoldFelixhough","winsRanked":8,"lossesRanked":2,"division":"FF","level":52,"eloRanked":1413,"eloChange":73,"rankChange":1138,"wins":-17,"losses":-25,"rank":197},{"id":331215,"username":"surawwa","winsRanked":0,"lossesRanked":1,"division":"FF","level":158,"eloRanked":1410,"eloChange":-111,"rankChange":477,"wins":-41,"losses":-37,"rank":198},{"id":384970,"username":"Alezf","winsRanked":1,"lossesRanked":1,"division":"FF","level":445,"eloRanked":1409,"eloChange":-100,"rankChange":512,"wins":-44,"losses":-45,"rank":199},{"id":380256,"username":"Puppet_Gaming","winsRanked":1,"lossesRanked":1,"division":"FF","level":383,"eloRanked":1407,"eloChange":-161,"rankChange":349,"wins":-49,"losses":-58,"rank":200},{"id":388187,"username":"Hubert Smalls","winsRanked":2,"lossesRanked":2,"division":"FF","level":315,"eloRanked":1407,"eloChange":-153,"rankChange":368,"wins":-48,"losses":-50,"rank":201},{"id":371312,"username":"bracalamo_rexx","winsRanked":2,"lossesRanked":0,"division":"FF","level":340,"eloRanked":1406,"eloChange":-128,"rankChange":434,"wins":-54,"losses":-53,"rank":202},{"id":774306,"username":"Bulbesta1000","winsRanked":3,"lossesRanked":7,"division":"FF","level":192,"eloRanked":1405,"eloChange":-158,"rankChange":358,"wins":-20,"losses":-13,"rank":203},{"id":391519,"username":"Derk bell","winsRanked":1,"lossesRanked":0,"division":"FF","level":350,"eloRanked":1404,"eloChange":-146,"rankChange":394,"wins":-49,"losses":-49,"rank":204},{"id":379114,"username":"Cally Whotsion","winsRanked":1,"lossesRanked":0,"division":"FF","level":347,"eloRanked":1404,"eloChange":-97,"rankChange":531,"wins":-56,"losses":-65,"rank":205},{"id":693347,"username":"Jollof","winsRanked":1,"lossesRanked":0,"division":"FF","level":271,"eloRanked":1401,"eloChange":-136,"rankChange":424,"wins":-3,"losses":-3,"rank":206},{"id":316285,"username":"ChujinKetsukane","winsRanked":2,"lossesRanked":1,"division":"FF","level":776,"eloRanked":1400,"eloChange":-99,"rankChange":533,"wins":-14,"losses":-2,"rank":207},{"id":377156,"username":"Shadowsomeone","winsRanked":1,"lossesRanked":1,"division":"FF","level":457,"eloRanked":1400,"eloChange":-90,"rankChange":568,"wins":-46,"losses":-51,"rank":208},{"id":376755,"username":"juanito765","winsRanked":3,"lossesRanked":3,"division":"FF","level":352,"eloRanked":1400,"eloChange":-89,"rankChange":577,"wins":-48,"losses":-58,"rank":209},{"id":389039,"username":"JoboXD","winsRanked":2,"lossesRanked":3,"division":"FF","level":373,"eloRanked":1400,"eloChange":-150,"rankChange":385,"wins":-53,"losses":-48,"rank":210},{"id":459588,"username":"Bolt45","winsRanked":1,"lossesRanked":8,"division":"FF","level":367,"eloRanked":1400,"eloChange":-253,"rankChange":171,"wins":-60,"losses":-46,"rank":211},{"id":399348,"username":"brocoleto","winsRanked":0,"lossesRanked":1,"division":"FF","level":452,"eloRanked":1400,"eloChange":-140,"rankChange":411,"wins":-53,"losses":-64,"rank":212},{"id":394161,"username":"idiita tale007","winsRanked":0,"lossesRanked":2,"division":"FF","level":347,"eloRanked":1400,"eloChange":-200,"rankChange":273,"wins":-57,"losses":-50,"rank":213},{"id":487351,"username":"SUCCET","winsRanked":1,"lossesRanked":0,"division":"F","level":201,"eloRanked":1399,"eloChange":-126,"rankChange":449,"wins":-4,"losses":-5,"rank":214},{"id":512059,"username":"Elias221q","winsRanked":1,"lossesRanked":2,"division":"F","level":365,"eloRanked":1399,"eloChange":-100,"rankChange":526,"wins":-16,"losses":-5,"rank":215},{"id":762955,"username":"Monito400","winsRanked":2,"lossesRanked":1,"division":"F","level":174,"eloRanked":1398,"eloChange":-103,"rankChange":515,"wins":-29,"losses":-24,"rank":216},{"id":44146,"username":"tyrell867","winsRanked":2,"lossesRanked":0,"division":"F","level":393,"eloRanked":1397,"eloChange":-75,"rankChange":607,"wins":-5,"losses":-5,"rank":217},{"id":780273,"username":"bimbus pumpany","winsRanked":4,"lossesRanked":0,"division":"F","level":7,"eloRanked":1396,"eloChange":-4,"rankChange":866,"wins":-5,"losses":-1,"rank":218},{"id":383039,"username":"Idoeoowiskskekw","winsRanked":2,"lossesRanked":0,"division":"F","level":422,"eloRanked":1391,"eloChange":-69,"rankChange":666,"wins":-41,"losses":-50,"rank":219},{"id":664254,"username":"Suki_Dreemurr","winsRanked":4,"lossesRanked":0,"division":"F","level":216,"eloRanked":1391,"eloChange":-20,"rankChange":823,"wins":-116,"losses":-155,"rank":220},{"id":446920,"username":"Raptor452","winsRanked":1,"lossesRanked":0,"division":"F","level":178,"eloRanked":1391,"eloChange":-99,"rankChange":545,"wins":-20,"losses":-10,"rank":221},{"id":757956,"username":"Sicking21","winsRanked":1,"lossesRanked":2,"division":"F","level":488,"eloRanked":1389,"eloChange":-168,"rankChange":358,"wins":-37,"losses":-49,"rank":222},{"id":612637,"username":"Creative Name","winsRanked":1,"lossesRanked":0,"division":"F","level":558,"eloRanked":1388,"eloChange":-107,"rankChange":524,"wins":-7,"losses":-4,"rank":223},{"id":374505,"username":"BruskSamnapona","winsRanked":2,"lossesRanked":2,"division":"F","level":324,"eloRanked":1387,"eloChange":-133,"rankChange":459,"wins":-47,"losses":-47,"rank":224},{"id":375174,"username":"Delta 1975","winsRanked":1,"lossesRanked":2,"division":"F","level":319,"eloRanked":1386,"eloChange":-157,"rankChange":388,"wins":-52,"losses":-60,"rank":225},{"id":208791,"username":"anthony la","winsRanked":2,"lossesRanked":10,"division":"F","level":288,"eloRanked":1383,"eloChange":-266,"rankChange":169,"wins":-43,"losses":-22,"rank":226},{"id":388994,"username":"sans22855","winsRanked":1,"lossesRanked":0,"division":"F","level":450,"eloRanked":1382,"eloChange":-108,"rankChange":547,"wins":-48,"losses":-51,"rank":227},{"id":370894,"username":"Kevin123cards","winsRanked":0,"lossesRanked":1,"division":"F","level":462,"eloRanked":1380,"eloChange":-170,"rankChange":374,"wins":-44,"losses":-46,"rank":228},{"id":377677,"username":"tobyleblanc","winsRanked":0,"lossesRanked":1,"division":"F","level":453,"eloRanked":1376,"eloChange":-145,"rankChange":447,"wins":-51,"losses":-54,"rank":229},{"id":329813,"username":"marmar204204","winsRanked":4,"lossesRanked":3,"division":"F","level":252,"eloRanked":1374,"eloChange":-116,"rankChange":550,"wins":-83,"losses":-104,"rank":230},{"id":393954,"username":"Kenshinloria","winsRanked":2,"lossesRanked":2,"division":"F","level":417,"eloRanked":1374,"eloChange":-121,"rankChange":518,"wins":-42,"losses":-47,"rank":231},{"id":774951,"username":"megadude16","winsRanked":8,"lossesRanked":8,"division":"F","level":144,"eloRanked":1373,"eloChange":-99,"rankChange":595,"wins":-51,"losses":-57,"rank":232},{"id":769684,"username":"Something143","winsRanked":0,"lossesRanked":1,"division":"F","level":142,"eloRanked":1373,"eloChange":-109,"rankChange":563,"wins":-89,"losses":-116,"rank":233},{"id":389078,"username":"Smiely","winsRanked":2,"lossesRanked":0,"division":"F","level":433,"eloRanked":1372,"eloChange":-82,"rankChange":661,"wins":-37,"losses":-55,"rank":234},{"id":633209,"username":"Doliousis","winsRanked":5,"lossesRanked":4,"division":"F","level":109,"eloRanked":1372,"eloChange":-18,"rankChange":891,"wins":0,"losses":0,"rank":235},{"id":743283,"username":"De Aster","winsRanked":1,"lossesRanked":0,"division":"F","level":949,"eloRanked":1371,"eloChange":-103,"rankChange":583,"wins":-10,"losses":-9,"rank":236},{"id":649181,"username":"hiiiiiiiiiiiiim","winsRanked":0,"lossesRanked":1,"division":"F","level":868,"eloRanked":1371,"eloChange":-179,"rankChange":360,"wins":-87,"losses":-84,"rank":237},{"id":435495,"username":"CosmicJester","winsRanked":5,"lossesRanked":2,"division":"F","level":185,"eloRanked":1370,"eloChange":14,"rankChange":1019,"wins":0,"losses":1,"rank":238},{"id":49044,"username":"netpet90","winsRanked":1,"lossesRanked":1,"division":"F","level":451,"eloRanked":1370,"eloChange":-120,"rankChange":529,"wins":-9,"losses":-5,"rank":239},{"id":390173,"username":"Sosso1603","winsRanked":1,"lossesRanked":1,"division":"F","level":323,"eloRanked":1370,"eloChange":-168,"rankChange":387,"wins":-49,"losses":-48,"rank":240},{"id":758770,"username":"KooperPlayz","winsRanked":3,"lossesRanked":3,"division":"F","level":136,"eloRanked":1370,"eloChange":-60,"rankChange":747,"wins":-35,"losses":-30,"rank":241},{"id":268299,"username":"Liamdjsbarnett","winsRanked":1,"lossesRanked":2,"division":"F","level":975,"eloRanked":1370,"eloChange":-162,"rankChange":401,"wins":-10,"losses":-5,"rank":242},{"id":513420,"username":"LilacQuinaceido","winsRanked":1,"lossesRanked":3,"division":"F","level":192,"eloRanked":1370,"eloChange":-181,"rankChange":346,"wins":-71,"losses":-63,"rank":243},{"id":779684,"username":"DeltaCardsWhen","winsRanked":1,"lossesRanked":3,"division":"F","level":177,"eloRanked":1370,"eloChange":-194,"rankChange":313,"wins":-212,"losses":-271,"rank":244},{"id":636001,"username":"Goldlibra","winsRanked":1,"lossesRanked":3,"division":"F","level":104,"eloRanked":1370,"rank":245},{"id":398203,"username":"Hagi","winsRanked":0,"lossesRanked":1,"division":"F","level":384,"eloRanked":1370,"eloChange":-180,"rankChange":355,"wins":-50,"losses":-52,"rank":246},{"id":96635,"username":"Gabe","winsRanked":0,"lossesRanked":2,"division":"F","level":675,"eloRanked":1370,"eloChange":-126,"rankChange":498,"wins":-129,"losses":-158,"rank":247},{"id":763942,"username":"Fort","winsRanked":3,"lossesRanked":2,"division":"GGG","level":234,"eloRanked":1369,"eloChange":5,"rankChange":984,"wins":-16,"losses":-24,"rank":248},{"id":384966,"username":"jotinha gatoooo","winsRanked":1,"lossesRanked":0,"division":"GGG","level":333,"eloRanked":1368,"eloChange":-92,"rankChange":634,"wins":-42,"losses":-40,"rank":249},{"id":650659,"username":"matoViva9","winsRanked":1,"lossesRanked":0,"division":"GGG","level":137,"eloRanked":1364,"eloChange":-88,"rankChange":655,"wins":-79,"losses":-95,"rank":250},{"id":780114,"username":"CF","winsRanked":6,"lossesRanked":12,"division":"GGG","level":178,"eloRanked":1364,"eloChange":-96,"rankChange":635,"wins":-267,"losses":-338,"rank":251},{"id":371783,"username":"NEON_Nick fox","winsRanked":2,"lossesRanked":2,"division":"GGG","level":369,"eloRanked":1363,"eloChange":-138,"rankChange":482,"wins":-54,"losses":-59,"rank":252},{"id":656031,"username":"ryankwok","winsRanked":1,"lossesRanked":0,"division":"GGG","level":289,"eloRanked":1362,"eloChange":-93,"rankChange":641,"wins":-12,"losses":-13,"rank":253},{"id":770831,"username":"Cattail","winsRanked":3,"lossesRanked":3,"division":"GGG","level":241,"eloRanked":1362,"eloChange":-116,"rankChange":552,"wins":-48,"losses":-50,"rank":254},{"id":385976,"username":"KOTYT2","winsRanked":1,"lossesRanked":1,"division":"GGG","level":361,"eloRanked":1360,"eloChange":-93,"rankChange":643,"wins":-48,"losses":-53,"rank":255},{"id":397155,"username":"Determinetion","winsRanked":1,"lossesRanked":1,"division":"GGG","level":308,"eloRanked":1360,"eloChange":-123,"rankChange":537,"wins":-49,"losses":-57,"rank":256},{"id":754314,"username":"zaus3","winsRanked":1,"lossesRanked":1,"division":"GGG","level":143,"eloRanked":1360,"eloChange":-128,"rankChange":531,"wins":-35,"losses":-44,"rank":257},{"id":385043,"username":"Nonikvanessa","winsRanked":2,"lossesRanked":1,"division":"GGG","level":292,"eloRanked":1359,"eloChange":-119,"rankChange":549,"wins":-45,"losses":-49,"rank":258},{"id":392093,"username":"Ryanhkendrick","winsRanked":1,"lossesRanked":2,"division":"GGG","level":460,"eloRanked":1356,"eloChange":-93,"rankChange":655,"wins":-42,"losses":-47,"rank":259},{"id":376209,"username":"Flameyboye","winsRanked":1,"lossesRanked":2,"division":"GGG","level":443,"eloRanked":1356,"eloChange":-116,"rankChange":568,"wins":-52,"losses":-57,"rank":260},{"id":773037,"username":"UnTrueReset","winsRanked":1,"lossesRanked":2,"division":"GGG","level":160,"eloRanked":1356,"eloChange":-184,"rankChange":360,"wins":-10,"losses":-8,"rank":261},{"id":385352,"username":"Seness","winsRanked":1,"lossesRanked":2,"division":"GGG","level":312,"eloRanked":1349,"eloChange":-141,"rankChange":513,"wins":-45,"losses":-48,"rank":262},{"id":578639,"username":"Darth_Nihilus","winsRanked":0,"lossesRanked":1,"division":"GGG","level":328,"eloRanked":1349,"eloChange":-152,"rankChange":470,"wins":-80,"losses":-85,"rank":263},{"id":522365,"username":"Mimer","winsRanked":0,"lossesRanked":3,"division":"GGG","level":301,"eloRanked":1348,"eloChange":-184,"rankChange":380,"wins":-76,"losses":-75,"rank":264},{"id":399294,"username":"AhmetBabaTR","winsRanked":1,"lossesRanked":0,"division":"GGG","level":340,"eloRanked":1343,"eloChange":-87,"rankChange":725,"wins":-51,"losses":-56,"rank":265},{"id":378221,"username":"Masonas","winsRanked":0,"lossesRanked":1,"division":"GGG","level":318,"eloRanked":1343,"eloChange":-141,"rankChange":525,"wins":-49,"losses":-47,"rank":266},{"id":764761,"username":"chillvibesfish","winsRanked":1,"lossesRanked":1,"division":"GGG","level":215,"eloRanked":1342,"eloChange":-119,"rankChange":603,"wins":-15,"losses":-8,"rank":267},{"id":81012,"username":"Thanasto","winsRanked":3,"lossesRanked":2,"division":"GGG","level":416,"eloRanked":1340,"rank":268},{"id":392810,"username":"Nin922","winsRanked":1,"lossesRanked":1,"division":"GGG","level":372,"eloRanked":1340,"eloChange":-100,"rankChange":680,"wins":-46,"losses":-50,"rank":269},{"id":770083,"username":"KingXcalibur","winsRanked":1,"lossesRanked":1,"division":"GGG","level":125,"eloRanked":1340,"eloChange":-100,"rankChange":678,"wins":-14,"losses":-9,"rank":270},{"id":495353,"username":"Eybuddy33","winsRanked":3,"lossesRanked":5,"division":"GGG","level":130,"eloRanked":1340,"eloChange":170,"rankChange":1913,"wins":2,"losses":3,"rank":271},{"id":4826,"username":"Rosario78","winsRanked":1,"lossesRanked":2,"division":"GGG","level":232,"eloRanked":1340,"eloChange":-172,"rankChange":432,"wins":-32,"losses":-28,"rank":272},{"id":493305,"username":"byeah","winsRanked":2,"lossesRanked":4,"division":"GGG","level":931,"eloRanked":1340,"eloChange":-93,"rankChange":696,"wins":-7,"losses":3,"rank":273},{"id":508180,"username":"Minimum_Wages","winsRanked":0,"lossesRanked":1,"division":"GGG","level":333,"eloRanked":1340,"eloChange":-131,"rankChange":559,"wins":-36,"losses":-29,"rank":274},{"id":748778,"username":"omigo86","winsRanked":1,"lossesRanked":0,"division":"GG","level":162,"eloRanked":1339,"eloChange":-92,"rankChange":704,"wins":-2,"losses":-1,"rank":275},{"id":375049,"username":"Sans.the.dark07","winsRanked":2,"lossesRanked":0,"division":"GG","level":333,"eloRanked":1336,"eloChange":-70,"rankChange":785,"wins":-46,"losses":-54,"rank":276},{"id":758319,"username":"SMG4Fan24","winsRanked":1,"lossesRanked":2,"division":"GG","level":682,"eloRanked":1334,"eloChange":-144,"rankChange":531,"wins":-85,"losses":-97,"rank":277},{"id":746596,"username":"Lolmanjr","winsRanked":3,"lossesRanked":1,"division":"GG","level":122,"eloRanked":1329,"eloChange":-42,"rankChange":928,"wins":-17,"losses":-17,"rank":278},{"id":762381,"username":"Pixie42","winsRanked":1,"lossesRanked":1,"division":"GG","level":171,"eloRanked":1329,"eloChange":-113,"rankChange":660,"wins":-4,"losses":-1,"rank":279},{"id":780345,"username":"Izetsu","winsRanked":1,"lossesRanked":1,"division":"GG","level":21,"eloRanked":1327,"eloChange":-109,"rankChange":682,"wins":-14,"losses":-4,"rank":280},{"id":756016,"username":"susiezilla","winsRanked":2,"lossesRanked":5,"division":"GG","level":265,"eloRanked":1326,"eloChange":-159,"rankChange":509,"wins":-3,"losses":2,"rank":281},{"id":469635,"username":"UnbiasedDiamond","winsRanked":1,"lossesRanked":0,"division":"GG","level":198,"eloRanked":1324,"eloChange":-81,"rankChange":784,"wins":-1,"losses":0,"rank":282},{"id":107734,"username":"AngelBoyLegit","winsRanked":1,"lossesRanked":2,"division":"GG","level":376,"eloRanked":1323,"eloChange":-96,"rankChange":743,"wins":-1,"losses":-2,"rank":283},{"id":1995,"username":"jack","winsRanked":4,"lossesRanked":9,"division":"GG","level":495,"eloRanked":1321,"eloChange":-153,"rankChange":536,"wins":-79,"losses":-103,"rank":284},{"id":203915,"username":"zinedine12!","winsRanked":1,"lossesRanked":3,"division":"GG","level":154,"eloRanked":1321,"eloChange":-88,"rankChange":767,"wins":-57,"losses":-72,"rank":285},{"id":466172,"username":"Rodion_smi","winsRanked":0,"lossesRanked":2,"division":"GG","level":790,"eloRanked":1321,"eloChange":-140,"rankChange":587,"wins":-72,"losses":-88,"rank":286},{"id":759062,"username":"jacky_0706","winsRanked":1,"lossesRanked":2,"division":"GG","level":89,"eloRanked":1319,"eloChange":-84,"rankChange":783,"wins":-23,"losses":-16,"rank":287},{"id":540015,"username":"Jalefh5","winsRanked":1,"lossesRanked":1,"division":"GG","level":27,"eloRanked":1316,"rank":288},{"id":390769,"username":"Bryangaming800","winsRanked":0,"lossesRanked":1,"division":"GG","level":427,"eloRanked":1316,"eloChange":-114,"rankChange":702,"wins":-46,"losses":-49,"rank":289},{"id":411093,"username":"kaeInsanity","winsRanked":1,"lossesRanked":2,"division":"GG","level":95,"eloRanked":1315,"rank":290},{"id":397802,"username":"felipexu1606","winsRanked":1,"lossesRanked":0,"division":"GG","level":382,"eloRanked":1312,"eloChange":-65,"rankChange":889,"wins":-24,"losses":-21,"rank":291},{"id":628627,"username":"javiboom","winsRanked":1,"lossesRanked":0,"division":"GG","level":172,"eloRanked":1312,"eloChange":-69,"rankChange":871,"wins":-16,"losses":-18,"rank":292},{"id":55540,"username":"coreyarmy","winsRanked":2,"lossesRanked":1,"division":"GG","level":2415,"eloRanked":1312,"eloChange":-74,"rankChange":848,"wins":-68,"losses":-87,"rank":293},{"id":396202,"username":"COOLGUY29182","winsRanked":2,"lossesRanked":3,"division":"GG","level":339,"eloRanked":1312,"eloChange":-86,"rankChange":809,"wins":-43,"losses":-54,"rank":294},{"id":779680,"username":"askz pet it,its","winsRanked":7,"lossesRanked":16,"division":"GG","level":120,"eloRanked":1312,"eloChange":-238,"rankChange":309,"wins":-217,"losses":-257,"rank":295},{"id":768346,"username":"88DEDGORL88","winsRanked":1,"lossesRanked":1,"division":"GG","level":74,"eloRanked":1310,"eloChange":-34,"rankChange":1012,"wins":-1,"losses":1,"rank":296},{"id":742349,"username":"{error404}","winsRanked":1,"lossesRanked":2,"division":"GG","level":527,"eloRanked":1310,"eloChange":-113,"rankChange":715,"wins":-109,"losses":-155,"rank":297},{"id":388215,"username":"Miniboru","winsRanked":1,"lossesRanked":2,"division":"GG","level":513,"eloRanked":1310,"eloChange":-78,"rankChange":835,"wins":-44,"losses":-62,"rank":298},{"id":395557,"username":"Destroyer13","winsRanked":0,"lossesRanked":1,"division":"GG","level":431,"eloRanked":1310,"eloChange":-158,"rankChange":545,"wins":-44,"losses":-55,"rank":299},{"id":58085,"username":"dogman250001","winsRanked":0,"lossesRanked":1,"division":"GG","level":121,"eloRanked":1310,"eloChange":-65,"rankChange":886,"wins":-12,"losses":-14,"rank":300},{"id":281616,"username":"NoxxyNox","winsRanked":0,"lossesRanked":4,"division":"GG","level":573,"eloRanked":1310,"eloChange":-191,"rankChange":431,"wins":-29,"losses":-27,"rank":301},{"id":780452,"username":"sxmethingHere","winsRanked":2,"lossesRanked":2,"division":"G","level":9,"eloRanked":1308,"rank":302},{"id":634658,"username":"tiggysummer","winsRanked":3,"lossesRanked":0,"division":"G","level":343,"eloRanked":1305,"eloChange":-4,"rankChange":1232,"wins":-2,"losses":-3,"rank":303},{"id":394389,"username":"Tim07super","winsRanked":1,"lossesRanked":1,"division":"G","level":419,"eloRanked":1302,"eloChange":-128,"rankChange":689,"wins":-42,"losses":-57,"rank":304},{"id":762900,"username":"moumou","winsRanked":1,"lossesRanked":0,"division":"G","level":247,"eloRanked":1301,"eloChange":-59,"rankChange":941,"wins":-8,"losses":-15,"rank":305},{"id":764034,"username":"pollytheparrot","winsRanked":1,"lossesRanked":0,"division":"G","level":175,"eloRanked":1301,"eloChange":-69,"rankChange":910,"wins":-9,"losses":-9,"rank":306},{"id":762391,"username":"Vins","winsRanked":5,"lossesRanked":1,"division":"G","level":26,"eloRanked":1300,"rank":307},{"id":392193,"username":"N L","winsRanked":2,"lossesRanked":1,"division":"G","level":333,"eloRanked":1300,"eloChange":-45,"rankChange":997,"wins":-44,"losses":-67,"rank":308},{"id":225193,"username":"matheuskaitos","winsRanked":2,"lossesRanked":1,"division":"G","level":614,"eloRanked":1298,"eloChange":-45,"rankChange":1005,"wins":-5,"losses":-5,"rank":309},{"id":399759,"username":"dragoforce12br","winsRanked":1,"lossesRanked":1,"division":"G","level":488,"eloRanked":1298,"eloChange":-119,"rankChange":719,"wins":-56,"losses":-68,"rank":310},{"id":379893,"username":"Totororo","winsRanked":2,"lossesRanked":1,"division":"G","level":429,"eloRanked":1297,"eloChange":-68,"rankChange":919,"wins":-40,"losses":-47,"rank":311},{"id":750180,"username":"Ryan10mb","winsRanked":1,"lossesRanked":0,"division":"G","level":35,"eloRanked":1295,"rank":312},{"id":674693,"username":"Alastair1","winsRanked":8,"lossesRanked":11,"division":"G","level":180,"eloRanked":1292,"eloChange":-99,"rankChange":809,"wins":-127,"losses":-188,"rank":313},{"id":376247,"username":"JonksMahBoye","winsRanked":2,"lossesRanked":0,"division":"G","level":316,"eloRanked":1291,"eloChange":-42,"rankChange":1044,"wins":-45,"losses":-66,"rank":314},{"id":659324,"username":"Dankboy","winsRanked":1,"lossesRanked":1,"division":"G","level":97,"eloRanked":1290,"eloChange":-80,"rankChange":899,"wins":-14,"losses":-11,"rank":315},{"id":77439,"username":"Blooky42","winsRanked":1,"lossesRanked":0,"division":"G","level":577,"eloRanked":1289,"eloChange":-14,"rankChange":1242,"wins":-1,"losses":-1,"rank":316},{"id":375832,"username":"Slaer","winsRanked":0,"lossesRanked":1,"division":"G","level":390,"eloRanked":1289,"eloChange":-129,"rankChange":711,"wins":-41,"losses":-41,"rank":317},{"id":371925,"username":"starstar243","winsRanked":0,"lossesRanked":1,"division":"G","level":369,"eloRanked":1288,"eloChange":-125,"rankChange":718,"wins":-5,"losses":-2,"rank":318},{"id":399874,"username":"Sanos_is_god","winsRanked":1,"lossesRanked":2,"division":"G","level":451,"eloRanked":1287,"eloChange":-113,"rankChange":775,"wins":-47,"losses":-58,"rank":319},{"id":489217,"username":"Avatarshow","winsRanked":0,"lossesRanked":1,"division":"G","level":892,"eloRanked":1287,"rank":320},{"id":752932,"username":"frogspawn","winsRanked":1,"lossesRanked":1,"division":"G","level":483,"eloRanked":1285,"eloChange":-115,"rankChange":772,"wins":-55,"losses":-65,"rank":321},{"id":761654,"username":"Blackmoretx","winsRanked":1,"lossesRanked":2,"division":"G","level":66,"eloRanked":1285,"eloChange":-98,"rankChange":830,"wins":-8,"losses":-5,"rank":322},{"id":738892,"username":"Screen_ghost","winsRanked":1,"lossesRanked":0,"division":"G","level":21,"eloRanked":1282,"eloChange":144,"rankChange":1925,"wins":-1,"losses":0,"rank":323},{"id":374633,"username":"Demiplaise","winsRanked":3,"lossesRanked":2,"division":"G","level":786,"eloRanked":1282,"eloChange":-56,"rankChange":1019,"wins":-4,"losses":0,"rank":324},{"id":780492,"username":"generic_br","winsRanked":10,"lossesRanked":4,"division":"G","level":7,"eloRanked":1280,"rank":325},{"id":397261,"username":"Sky(Chara)","winsRanked":0,"lossesRanked":1,"division":"G","level":363,"eloRanked":1280,"eloChange":-101,"rankChange":840,"wins":-54,"losses":-72,"rank":326},{"id":647800,"username":"brbregister","winsRanked":0,"lossesRanked":1,"division":"G","level":309,"eloRanked":1280,"eloChange":-106,"rankChange":813,"wins":-6,"losses":-5,"rank":327},{"id":650937,"username":"ElTabalis","winsRanked":0,"lossesRanked":1,"division":"G","level":204,"eloRanked":1280,"eloChange":-122,"rankChange":747,"wins":-10,"losses":-5,"rank":328},{"id":759443,"username":"Voiditect","winsRanked":0,"lossesRanked":1,"division":"G","level":177,"eloRanked":1280,"eloChange":-123,"rankChange":744,"wins":-33,"losses":-40,"rank":329},{"id":762142,"username":"Shrugs","winsRanked":0,"lossesRanked":1,"division":"G","level":84,"eloRanked":1280,"eloChange":71,"rankChange":1735,"wins":-6,"losses":-4,"rank":330},{"id":520077,"username":"Canela_Dog","winsRanked":2,"lossesRanked":0,"division":"HHH","level":213,"eloRanked":1279,"eloChange":-33,"rankChange":1153,"wins":-2,"losses":-4,"rank":331},{"id":380844,"username":"Suka ebanaya","winsRanked":1,"lossesRanked":0,"division":"HHH","level":409,"eloRanked":1272,"eloChange":-68,"rankChange":1004,"wins":-39,"losses":-51,"rank":332},{"id":611380,"username":"Zombie115","winsRanked":1,"lossesRanked":0,"division":"HHH","level":26,"eloRanked":1268,"eloChange":-56,"rankChange":1067,"wins":-7,"losses":-4,"rank":333},{"id":466101,"username":"Lango_Stino","winsRanked":6,"lossesRanked":3,"division":"HHH","level":29,"eloRanked":1267,"rank":334},{"id":779643,"username":"Azzyky","winsRanked":3,"lossesRanked":4,"division":"HHH","level":62,"eloRanked":1264,"eloChange":-87,"rankChange":947,"wins":-97,"losses":-125,"rank":335},{"id":758382,"username":"JTC72","winsRanked":1,"lossesRanked":0,"division":"HHH","level":317,"eloRanked":1263,"eloChange":-32,"rankChange":1262,"wins":-13,"losses":-22,"rank":336},{"id":15970,"username":"FishtankPlays","winsRanked":1,"lossesRanked":2,"division":"HHH","level":54,"eloRanked":1262,"eloChange":-32,"rankChange":1267,"wins":-26,"losses":-29,"rank":337},{"id":743314,"username":"MrMeme97","winsRanked":1,"lossesRanked":4,"division":"HHH","level":75,"eloRanked":1261,"eloChange":-160,"rankChange":680,"wins":-67,"losses":-77,"rank":338},{"id":372875,"username":"sansisepic2334","winsRanked":2,"lossesRanked":0,"division":"HHH","level":289,"eloRanked":1258,"eloChange":20,"rankChange":1572,"wins":-32,"losses":-51,"rank":339},{"id":725650,"username":"kidvenison2010","winsRanked":2,"lossesRanked":1,"division":"HHH","level":34,"eloRanked":1255,"eloChange":5,"rankChange":1517,"wins":-8,"losses":-8,"rank":340},{"id":757312,"username":"Duckadoo22","winsRanked":3,"lossesRanked":1,"division":"HHH","level":143,"eloRanked":1250,"rank":341},{"id":742966,"username":"#blooky","winsRanked":3,"lossesRanked":5,"division":"HHH","level":35,"eloRanked":1250,"rank":342},{"id":114353,"username":"Nightmarespring","winsRanked":0,"lossesRanked":3,"division":"HHH","level":130,"eloRanked":1250,"eloChange":-143,"rankChange":769,"wins":-36,"losses":-31,"rank":343},{"id":362050,"username":"CaffeinatedHK","winsRanked":1,"lossesRanked":0,"division":"HH","level":1171,"eloRanked":1240,"eloChange":-56,"rankChange":1245,"wins":-6,"losses":-3,"rank":344},{"id":383165,"username":"UnderMonster","winsRanked":1,"lossesRanked":0,"division":"HH","level":268,"eloRanked":1240,"eloChange":-12,"rankChange":1491,"wins":-19,"losses":-26,"rank":345},{"id":378546,"username":"DenisUltra","winsRanked":1,"lossesRanked":1,"division":"HH","level":353,"eloRanked":1238,"eloChange":-117,"rankChange":918,"wins":-50,"losses":-72,"rank":346},{"id":728849,"username":"Boris_1","winsRanked":1,"lossesRanked":0,"division":"HH","level":37,"eloRanked":1232,"rank":347},{"id":393967,"username":"Bradett","winsRanked":2,"lossesRanked":1,"division":"HH","level":356,"eloRanked":1225,"eloChange":-43,"rankChange":1412,"wins":-36,"losses":-49,"rank":348},{"id":757241,"username":"Goosie","winsRanked":2,"lossesRanked":0,"division":"HH","level":35,"eloRanked":1224,"eloChange":11,"rankChange":1698,"wins":-40,"losses":-53,"rank":349},{"id":652775,"username":"21carsmlg","winsRanked":4,"lossesRanked":5,"division":"HH","level":74,"eloRanked":1221,"eloChange":-71,"rankChange":1258,"wins":-5,"losses":-3,"rank":350},{"id":3261,"username":"ToHeckAndBack","winsRanked":2,"lossesRanked":1,"division":"HH","level":89,"eloRanked":1220,"rank":351},{"id":772164,"username":"ShiningSceptile","winsRanked":5,"lossesRanked":4,"division":"HH","level":14,"eloRanked":1220,"rank":352},{"id":780466,"username":"housebox78","winsRanked":2,"lossesRanked":2,"division":"HH","level":11,"eloRanked":1220,"rank":353},{"id":780443,"username":"Fire_Penguin","winsRanked":2,"lossesRanked":4,"division":"HH","level":16,"eloRanked":1220,"eloChange":21,"rankChange":1744,"wins":-2,"losses":1,"rank":354},{"id":487784,"username":"NoobyChara","winsRanked":0,"lossesRanked":1,"division":"HH","level":710,"eloRanked":1220,"eloChange":-71,"rankChange":1262,"wins":-7,"losses":-3,"rank":355},{"id":146243,"username":"Hailey lay","winsRanked":0,"lossesRanked":1,"division":"HH","level":215,"eloRanked":1220,"eloChange":-63,"rankChange":1304,"wins":-16,"losses":-10,"rank":356},{"id":314928,"username":"#UndertaleLover","winsRanked":1,"lossesRanked":0,"division":"H","level":92,"eloRanked":1219,"rank":357},{"id":371261,"username":"JakersQuakers","winsRanked":2,"lossesRanked":1,"division":"H","level":182,"eloRanked":1217,"eloChange":-33,"rankChange":1501,"wins":0,"losses":-1,"rank":358},{"id":778707,"username":"Ministy","winsRanked":1,"lossesRanked":0,"division":"H","level":13,"eloRanked":1213,"eloChange":-28,"rankChange":1544,"wins":-3,"losses":-3,"rank":359},{"id":635420,"username":"ir315max","winsRanked":1,"lossesRanked":1,"division":"H","level":32,"eloRanked":1211,"rank":360},{"id":655564,"username":"le trolleurYT","winsRanked":1,"lossesRanked":0,"division":"H","level":28,"eloRanked":1205,"eloChange":-25,"rankChange":1587,"wins":-45,"losses":-61,"rank":361},{"id":617615,"username":"Melancholy22","winsRanked":1,"lossesRanked":5,"division":"H","level":32,"eloRanked":1204,"eloChange":-98,"rankChange":1201,"wins":-19,"losses":-20,"rank":362},{"id":764697,"username":"Chachis","winsRanked":1,"lossesRanked":0,"division":"H","level":57,"eloRanked":1201,"eloChange":-32,"rankChange":1570,"wins":-96,"losses":-147,"rank":363},{"id":671819,"username":"Cusifr","winsRanked":1,"lossesRanked":1,"division":"H","level":183,"eloRanked":1194,"eloChange":-40,"rankChange":1557,"wins":-2,"losses":-2,"rank":364},{"id":779703,"username":"SKirilll01","winsRanked":1,"lossesRanked":1,"division":"H","level":16,"eloRanked":1193,"eloChange":-40,"rankChange":1565,"wins":-19,"losses":-24,"rank":365},{"id":777304,"username":"V0cad0","winsRanked":1,"lossesRanked":1,"division":"H","level":8,"eloRanked":1190,"rank":366},{"id":764393,"username":"BLASHROD","winsRanked":1,"lossesRanked":2,"division":"H","level":15,"eloRanked":1190,"rank":367},{"id":780462,"username":"Xx_Wizard_xX","winsRanked":0,"lossesRanked":1,"division":"H","level":8,"eloRanked":1190,"rank":368},{"id":779378,"username":"BeDaHappy","winsRanked":1,"lossesRanked":0,"division":"ZZZ","level":19,"eloRanked":1168,"eloChange":-6,"rankChange":1803,"wins":-2,"losses":-5,"rank":369},{"id":770333,"username":"thebringerofbea","winsRanked":0,"lossesRanked":1,"division":"ZZZ","level":27,"eloRanked":1165,"eloChange":-55,"rankChange":1638,"wins":-21,"losses":-21,"rank":370},{"id":725947,"username":"TallishCookie62","winsRanked":0,"lossesRanked":1,"division":"ZZZ","level":181,"eloRanked":1160,"eloChange":-59,"rankChange":1669,"wins":-3,"losses":-6,"rank":371},{"id":758358,"username":"Bird_le_Froggit","winsRanked":0,"lossesRanked":2,"division":"ZZZ","level":69,"eloRanked":1160,"eloChange":-63,"rankChange":1613,"wins":-9,"losses":-13,"rank":372},{"id":620174,"username":"CreeperSoul128","winsRanked":1,"lossesRanked":0,"division":"ZZ","level":6,"eloRanked":1145,"eloChange":6,"rankChange":1872,"wins":-1,"losses":-1,"rank":373},{"id":374832,"username":"Killer28","winsRanked":1,"lossesRanked":2,"division":"ZZ","level":327,"eloRanked":1144,"eloChange":-50,"rankChange":1736,"wins":-17,"losses":-27,"rank":374},{"id":383038,"username":"Salt76","winsRanked":1,"lossesRanked":0,"division":"Z","level":153,"eloRanked":1124,"eloChange":24,"rankChange":1939,"wins":-11,"losses":-33,"rank":375},{"id":780491,"username":"SnoaringKnight","winsRanked":1,"lossesRanked":1,"division":"Z","level":5,"eloRanked":1102,"rank":376},{"id":762800,"username":"ThatScottster24","winsRanked":0,"lossesRanked":1,"division":"Z","level":14,"eloRanked":1100,"eloChange":-30,"rankChange":1900,"wins":0,"losses":-1,"rank":377}]